{"v":"5.7.4","fr":29.9700012207031,"ip":0,"op":150.000006109625,"w":1700,"h":1280,"nm":"HomeAnim-3","ddd":0,"assets":[{"id":"image_0","w":72,"h":32,"u":"images/","p":"img_0.png","e":0},{"id":"image_1","w":146,"h":32,"u":"images/","p":"img_1.png","e":0},{"id":"image_2","w":146,"h":32,"u":"images/","p":"img_2.png","e":0},{"id":"image_3","w":106,"h":32,"u":"images/","p":"img_3.png","e":0},{"id":"image_4","w":22,"h":20,"u":"images/","p":"img_4.png","e":0},{"id":"image_5","w":498,"h":336,"u":"images/","p":"img_5.png","e":0},{"id":"image_6","w":356,"h":614,"u":"images/","p":"img_6.png","e":0},{"id":"image_7","w":872,"h":186,"u":"images/","p":"img_7.png","e":0},{"id":"image_8","w":228,"h":186,"u":"images/","p":"img_8.png","e":0},{"id":"image_9","w":228,"h":186,"u":"images/","p":"img_9.png","e":0},{"id":"image_10","w":228,"h":186,"u":"images/","p":"img_10.png","e":0},{"id":"image_11","w":228,"h":186,"u":"images/","p":"img_11.png","e":0},{"id":"image_12","w":228,"h":186,"u":"images/","p":"img_12.png","e":0},{"id":"image_13","w":228,"h":186,"u":"images/","p":"img_13.png","e":0},{"id":"image_14","w":1656,"h":1394,"u":"images/","p":"img_14.png","e":0}],"fonts":{"list":[{"fName":"NunitoSans-ExtraBold","fFamily":"Nunito Sans","fStyle":"ExtraBold","ascent":70.4986572265625},{"fName":"NotoSansTC-Bold","fFamily":"Noto Sans TC Bold","fStyle":"Regular","ascent":79.7988891601562}]},"layers":[{"ddd":0,"ind":1,"ty":2,"nm":"testStep-4-@2x.png","cl":"png","refId":"image_0","sr":1,"ks":{"o":{"a":0,"k":100,"ix":11,"x":"var $bm_rt;\nvar result;\nresult = getAnimationComposerPresetValue();\nfunction getAnimationComposerPresetValue() {\n    var bL = thisLayer;\n    var tTrI = null;\n    var tTrO = null;\n    if (bL.marker.numKeys > 0) {\n        var acmp = 'zzzzzzzzzzzzzzz_AC';\n        for (var i = 1; i <= bL.marker.numKeys; i++) {\n            var m = bL.marker.key(i);\n            var p = m.parameters;\n            if (p.hasOwnProperty(acmp + 'MarkerEnabled') && p.hasOwnProperty(acmp + 'MarkerType') && p.hasOwnProperty(acmp + 'MarkerAppPresetType')) {\n                if (p[acmp + 'MarkerEnabled'] != '1') {\n                    continue;\n                }\n                switch (p[acmp + 'MarkerAppPresetType']) {\n                case '1': {\n                        tTrI = m.time;\n                        break;\n                    }\n                }\n            }\n        }\n    }\n    ;\n    function acPD(fxN) {\n        try {\n            if (bL.effect(fxN).active === false) {\n                ac.en = false;\n            }\n        } catch (e) {\n        }\n    }\n    function acValMul(val) {\n        acAccM *= val;\n    }\n    function easeInQuint(t) {\n        return $bm_mul($bm_mul($bm_mul($bm_mul(t, t), t), t), t);\n    }\n    function upACo(tIn, dIn, tOut, dOut, eFi, eFo) {\n        if (dIn < 0) {\n            dIn = 0;\n        }\n        if (dOut < 0) {\n            dOut = 0;\n        }\n        ac.fade = 1;\n        if (t < tOut) {\n            if (t < $bm_sum(tIn, dIn)) {\n                if (dIn == 0) {\n                    ac.fade = 0;\n                } else {\n                    ac.fade = $bm_div($bm_sub(t, tIn), dIn);\n                    if (ac.fade < 0) {\n                        ac.fade = 0;\n                    }\n                    if (ac.fade > 1) {\n                        ac.fade = 1;\n                    }\n                    if (eFi) {\n                        ac.fade = eFi(ac.fade);\n                    }\n                }\n            }\n        } else {\n            if (dOut == 0) {\n                ac.fade = 0;\n            } else {\n                ac.fade = $bm_div($bm_sub(t, tOut), dOut);\n                if (ac.fade < 0) {\n                    ac.fade = 0;\n                }\n                if (ac.fade > 1) {\n                    ac.fade = 1;\n                }\n                if (eFo) {\n                    ac.fade = eFo(ac.fade);\n                }\n                ac.fade = $bm_sub(1, ac.fade);\n            }\n        }\n        ac.intensity = 1;\n        ac.en = true;\n        ac.t = $bm_sub(t, tIn);\n    }\n    var ac = {};\n    ac.en = false;\n    var v = thisProperty.value;\n    var t = time;\n    var acAccM = 1;\n    ac.en = false;\n    if (tTrI !== null && t < tTrI) {\n        upACo(bL.inPoint, $bm_sub(tTrI, bL.inPoint), bL.outPoint, 0);\n        ac.fade = $bm_sub(1, ac.fade);\n    }\n    acPD('AC IN [XUT] Controls');\n    if (ac.en) {\n        acValMul($bm_sub(1, easeInQuint(ac.fade)));\n    }\n    v = thisProperty.value;\n    v *= acAccM;\n    return v;\n}\n$bm_rt = result;"},"r":{"a":0,"k":0,"ix":10},"p":{"a":0,"k":[534,1140,0],"ix":2,"x":"var $bm_rt;\nvar result;\nresult = getAnimationComposerPresetValue();\nfunction getAnimationComposerPresetValue() {\n    var bL = thisLayer;\n    var tTrI = null;\n    var tTrO = null;\n    if (bL.marker.numKeys > 0) {\n        var acmp = 'zzzzzzzzzzzzzzz_AC';\n        for (var i = 1; i <= bL.marker.numKeys; i++) {\n            var m = bL.marker.key(i);\n            var p = m.parameters;\n            if (p.hasOwnProperty(acmp + 'MarkerEnabled') && p.hasOwnProperty(acmp + 'MarkerType') && p.hasOwnProperty(acmp + 'MarkerAppPresetType')) {\n                if (p[acmp + 'MarkerEnabled'] != '1') {\n                    continue;\n                }\n                switch (p[acmp + 'MarkerAppPresetType']) {\n                case '1': {\n                        tTrI = m.time;\n                        break;\n                    }\n                }\n            }\n        }\n    }\n    ;\n    function acPD(fxN) {\n        try {\n            if (bL.effect(fxN).active === false) {\n                ac.en = false;\n            }\n        } catch (e) {\n        }\n    }\n    function acPointValP(fxN, stN, dV) {\n        try {\n            return bL.effect(fxN)(stN);\n        } catch (e) {\n            return dV;\n        }\n    }\n    function acValAdd(val) {\n        acAccA = $bm_sum(acAccA, val);\n    }\n    function easeInCubic(t) {\n        return $bm_mul($bm_mul(t, t), t);\n    }\n    function upACo(tIn, dIn, tOut, dOut, eFi, eFo) {\n        if (dIn < 0) {\n            dIn = 0;\n        }\n        if (dOut < 0) {\n            dOut = 0;\n        }\n        ac.fade = 1;\n        if (t < tOut) {\n            if (t < $bm_sum(tIn, dIn)) {\n                if (dIn == 0) {\n                    ac.fade = 0;\n                } else {\n                    ac.fade = $bm_div($bm_sub(t, tIn), dIn);\n                    if (ac.fade < 0) {\n                        ac.fade = 0;\n                    }\n                    if (ac.fade > 1) {\n                        ac.fade = 1;\n                    }\n                    if (eFi) {\n                        ac.fade = eFi(ac.fade);\n                    }\n                }\n            }\n        } else {\n            if (dOut == 0) {\n                ac.fade = 0;\n            } else {\n                ac.fade = $bm_div($bm_sub(t, tOut), dOut);\n                if (ac.fade < 0) {\n                    ac.fade = 0;\n                }\n                if (ac.fade > 1) {\n                    ac.fade = 1;\n                }\n                if (eFo) {\n                    ac.fade = eFo(ac.fade);\n                }\n                ac.fade = $bm_sub(1, ac.fade);\n            }\n        }\n        ac.intensity = 1;\n        ac.en = true;\n        ac.t = $bm_sub(t, tIn);\n    }\n    var ac = {};\n    ac.en = false;\n    var v = thisProperty.value;\n    var t = time;\n    var acAccA = 0;\n    ac.en = false;\n    if (tTrI !== null && t < tTrI) {\n        upACo(bL.inPoint, $bm_sub(tTrI, bL.inPoint), bL.outPoint, 0);\n        ac.fade = $bm_sub(1, ac.fade);\n    }\n    acPD('AC IN [XUT] Controls');\n    if (ac.en) {\n        acValAdd($bm_mul(acPointValP('AC IN [XUT] Controls', 'Position', [\n            0,\n            200\n        ]), easeInCubic(ac.fade)));\n    }\n    v = thisProperty.value;\n    v = $bm_sum(v, acAccA);\n    return v;\n}\n$bm_rt = result;","l":2},"a":{"a":0,"k":[36,16,0],"ix":1,"l":2},"s":{"a":0,"k":[100,100,100],"ix":6,"l":2}},"ao":0,"ef":[{"ty":5,"nm":"AC IN [XUT] Controls","np":3,"mn":"Pseudo/MHAC PrCtrl XUT 3","ix":1,"en":1,"ef":[{"ty":3,"nm":"Position","mn":"Pseudo/MHAC PrCtrl XUT 3-0001","ix":1,"v":{"a":0,"k":[0,60],"ix":1}}]}],"ip":78.0000031770051,"op":150.000006109625,"st":24.00000097754,"bm":0},{"ddd":0,"ind":2,"ty":2,"nm":"testStep-3-@2x.png","cl":"png","refId":"image_1","sr":1,"ks":{"o":{"a":0,"k":100,"ix":11,"x":"var $bm_rt;\nvar result;\nresult = getAnimationComposerPresetValue();\nfunction getAnimationComposerPresetValue() {\n    var bL = thisLayer;\n    var tTrI = null;\n    var tTrO = null;\n    if (bL.marker.numKeys > 0) {\n        var acmp = 'zzzzzzzzzzzzzzz_AC';\n        for (var i = 1; i <= bL.marker.numKeys; i++) {\n            var m = bL.marker.key(i);\n            var p = m.parameters;\n            if (p.hasOwnProperty(acmp + 'MarkerEnabled') && p.hasOwnProperty(acmp + 'MarkerType') && p.hasOwnProperty(acmp + 'MarkerAppPresetType')) {\n                if (p[acmp + 'MarkerEnabled'] != '1') {\n                    continue;\n                }\n                switch (p[acmp + 'MarkerAppPresetType']) {\n                case '1': {\n                        tTrI = m.time;\n                        break;\n                    }\n                }\n            }\n        }\n    }\n    ;\n    function acPD(fxN) {\n        try {\n            if (bL.effect(fxN).active === false) {\n                ac.en = false;\n            }\n        } catch (e) {\n        }\n    }\n    function acValMul(val) {\n        acAccM *= val;\n    }\n    function easeInQuint(t) {\n        return $bm_mul($bm_mul($bm_mul($bm_mul(t, t), t), t), t);\n    }\n    function upACo(tIn, dIn, tOut, dOut, eFi, eFo) {\n        if (dIn < 0) {\n            dIn = 0;\n        }\n        if (dOut < 0) {\n            dOut = 0;\n        }\n        ac.fade = 1;\n        if (t < tOut) {\n            if (t < $bm_sum(tIn, dIn)) {\n                if (dIn == 0) {\n                    ac.fade = 0;\n                } else {\n                    ac.fade = $bm_div($bm_sub(t, tIn), dIn);\n                    if (ac.fade < 0) {\n                        ac.fade = 0;\n                    }\n                    if (ac.fade > 1) {\n                        ac.fade = 1;\n                    }\n                    if (eFi) {\n                        ac.fade = eFi(ac.fade);\n                    }\n                }\n            }\n        } else {\n            if (dOut == 0) {\n                ac.fade = 0;\n            } else {\n                ac.fade = $bm_div($bm_sub(t, tOut), dOut);\n                if (ac.fade < 0) {\n                    ac.fade = 0;\n                }\n                if (ac.fade > 1) {\n                    ac.fade = 1;\n                }\n                if (eFo) {\n                    ac.fade = eFo(ac.fade);\n                }\n                ac.fade = $bm_sub(1, ac.fade);\n            }\n        }\n        ac.intensity = 1;\n        ac.en = true;\n        ac.t = $bm_sub(t, tIn);\n    }\n    var ac = {};\n    ac.en = false;\n    var v = thisProperty.value;\n    var t = time;\n    var acAccM = 1;\n    ac.en = false;\n    if (tTrI !== null && t < tTrI) {\n        upACo(bL.inPoint, $bm_sub(tTrI, bL.inPoint), bL.outPoint, 0);\n        ac.fade = $bm_sub(1, ac.fade);\n    }\n    acPD('AC IN [XUT] Controls');\n    if (ac.en) {\n        acValMul($bm_sub(1, easeInQuint(ac.fade)));\n    }\n    v = thisProperty.value;\n    v *= acAccM;\n    return v;\n}\n$bm_rt = result;"},"r":{"a":0,"k":0,"ix":10},"p":{"a":0,"k":[571,1098,0],"ix":2,"x":"var $bm_rt;\nvar result;\nresult = getAnimationComposerPresetValue();\nfunction getAnimationComposerPresetValue() {\n    var bL = thisLayer;\n    var tTrI = null;\n    var tTrO = null;\n    if (bL.marker.numKeys > 0) {\n        var acmp = 'zzzzzzzzzzzzzzz_AC';\n        for (var i = 1; i <= bL.marker.numKeys; i++) {\n            var m = bL.marker.key(i);\n            var p = m.parameters;\n            if (p.hasOwnProperty(acmp + 'MarkerEnabled') && p.hasOwnProperty(acmp + 'MarkerType') && p.hasOwnProperty(acmp + 'MarkerAppPresetType')) {\n                if (p[acmp + 'MarkerEnabled'] != '1') {\n                    continue;\n                }\n                switch (p[acmp + 'MarkerAppPresetType']) {\n                case '1': {\n                        tTrI = m.time;\n                        break;\n                    }\n                }\n            }\n        }\n    }\n    ;\n    function acPD(fxN) {\n        try {\n            if (bL.effect(fxN).active === false) {\n                ac.en = false;\n            }\n        } catch (e) {\n        }\n    }\n    function acPointValP(fxN, stN, dV) {\n        try {\n            return bL.effect(fxN)(stN);\n        } catch (e) {\n            return dV;\n        }\n    }\n    function acValAdd(val) {\n        acAccA = $bm_sum(acAccA, val);\n    }\n    function easeInCubic(t) {\n        return $bm_mul($bm_mul(t, t), t);\n    }\n    function upACo(tIn, dIn, tOut, dOut, eFi, eFo) {\n        if (dIn < 0) {\n            dIn = 0;\n        }\n        if (dOut < 0) {\n            dOut = 0;\n        }\n        ac.fade = 1;\n        if (t < tOut) {\n            if (t < $bm_sum(tIn, dIn)) {\n                if (dIn == 0) {\n                    ac.fade = 0;\n                } else {\n                    ac.fade = $bm_div($bm_sub(t, tIn), dIn);\n                    if (ac.fade < 0) {\n                        ac.fade = 0;\n                    }\n                    if (ac.fade > 1) {\n                        ac.fade = 1;\n                    }\n                    if (eFi) {\n                        ac.fade = eFi(ac.fade);\n                    }\n                }\n            }\n        } else {\n            if (dOut == 0) {\n                ac.fade = 0;\n            } else {\n                ac.fade = $bm_div($bm_sub(t, tOut), dOut);\n                if (ac.fade < 0) {\n                    ac.fade = 0;\n                }\n                if (ac.fade > 1) {\n                    ac.fade = 1;\n                }\n                if (eFo) {\n                    ac.fade = eFo(ac.fade);\n                }\n                ac.fade = $bm_sub(1, ac.fade);\n            }\n        }\n        ac.intensity = 1;\n        ac.en = true;\n        ac.t = $bm_sub(t, tIn);\n    }\n    var ac = {};\n    ac.en = false;\n    var v = thisProperty.value;\n    var t = time;\n    var acAccA = 0;\n    ac.en = false;\n    if (tTrI !== null && t < tTrI) {\n        upACo(bL.inPoint, $bm_sub(tTrI, bL.inPoint), bL.outPoint, 0);\n        ac.fade = $bm_sub(1, ac.fade);\n    }\n    acPD('AC IN [XUT] Controls');\n    if (ac.en) {\n        acValAdd($bm_mul(acPointValP('AC IN [XUT] Controls', 'Position', [\n            0,\n            200\n        ]), easeInCubic(ac.fade)));\n    }\n    v = thisProperty.value;\n    v = $bm_sum(v, acAccA);\n    return v;\n}\n$bm_rt = result;","l":2},"a":{"a":0,"k":[73,16,0],"ix":1,"l":2},"s":{"a":0,"k":[100,100,100],"ix":6,"l":2}},"ao":0,"ef":[{"ty":5,"nm":"AC IN [XUT] Controls","np":3,"mn":"Pseudo/MHAC PrCtrl XUT 3","ix":1,"en":1,"ef":[{"ty":3,"nm":"Position","mn":"Pseudo/MHAC PrCtrl XUT 3-0001","ix":1,"v":{"a":0,"k":[0,60],"ix":1}}]}],"ip":70.0000028511585,"op":150.000006109625,"st":16.0000006516934,"bm":0},{"ddd":0,"ind":3,"ty":2,"nm":"testStep-2-@2x.png","cl":"png","refId":"image_2","sr":1,"ks":{"o":{"a":0,"k":100,"ix":11,"x":"var $bm_rt;\nvar result;\nresult = getAnimationComposerPresetValue();\nfunction getAnimationComposerPresetValue() {\n    var bL = thisLayer;\n    var tTrI = null;\n    var tTrO = null;\n    if (bL.marker.numKeys > 0) {\n        var acmp = 'zzzzzzzzzzzzzzz_AC';\n        for (var i = 1; i <= bL.marker.numKeys; i++) {\n            var m = bL.marker.key(i);\n            var p = m.parameters;\n            if (p.hasOwnProperty(acmp + 'MarkerEnabled') && p.hasOwnProperty(acmp + 'MarkerType') && p.hasOwnProperty(acmp + 'MarkerAppPresetType')) {\n                if (p[acmp + 'MarkerEnabled'] != '1') {\n                    continue;\n                }\n                switch (p[acmp + 'MarkerAppPresetType']) {\n                case '1': {\n                        tTrI = m.time;\n                        break;\n                    }\n                }\n            }\n        }\n    }\n    ;\n    function acPD(fxN) {\n        try {\n            if (bL.effect(fxN).active === false) {\n                ac.en = false;\n            }\n        } catch (e) {\n        }\n    }\n    function acValMul(val) {\n        acAccM *= val;\n    }\n    function easeInQuint(t) {\n        return $bm_mul($bm_mul($bm_mul($bm_mul(t, t), t), t), t);\n    }\n    function upACo(tIn, dIn, tOut, dOut, eFi, eFo) {\n        if (dIn < 0) {\n            dIn = 0;\n        }\n        if (dOut < 0) {\n            dOut = 0;\n        }\n        ac.fade = 1;\n        if (t < tOut) {\n            if (t < $bm_sum(tIn, dIn)) {\n                if (dIn == 0) {\n                    ac.fade = 0;\n                } else {\n                    ac.fade = $bm_div($bm_sub(t, tIn), dIn);\n                    if (ac.fade < 0) {\n                        ac.fade = 0;\n                    }\n                    if (ac.fade > 1) {\n                        ac.fade = 1;\n                    }\n                    if (eFi) {\n                        ac.fade = eFi(ac.fade);\n                    }\n                }\n            }\n        } else {\n            if (dOut == 0) {\n                ac.fade = 0;\n            } else {\n                ac.fade = $bm_div($bm_sub(t, tOut), dOut);\n                if (ac.fade < 0) {\n                    ac.fade = 0;\n                }\n                if (ac.fade > 1) {\n                    ac.fade = 1;\n                }\n                if (eFo) {\n                    ac.fade = eFo(ac.fade);\n                }\n                ac.fade = $bm_sub(1, ac.fade);\n            }\n        }\n        ac.intensity = 1;\n        ac.en = true;\n        ac.t = $bm_sub(t, tIn);\n    }\n    var ac = {};\n    ac.en = false;\n    var v = thisProperty.value;\n    var t = time;\n    var acAccM = 1;\n    ac.en = false;\n    if (tTrI !== null && t < tTrI) {\n        upACo(bL.inPoint, $bm_sub(tTrI, bL.inPoint), bL.outPoint, 0);\n        ac.fade = $bm_sub(1, ac.fade);\n    }\n    acPD('AC IN [XUT] Controls');\n    if (ac.en) {\n        acValMul($bm_sub(1, easeInQuint(ac.fade)));\n    }\n    v = thisProperty.value;\n    v *= acAccM;\n    return v;\n}\n$bm_rt = result;"},"r":{"a":0,"k":0,"ix":10},"p":{"a":0,"k":[571,1056,0],"ix":2,"x":"var $bm_rt;\nvar result;\nresult = getAnimationComposerPresetValue();\nfunction getAnimationComposerPresetValue() {\n    var bL = thisLayer;\n    var tTrI = null;\n    var tTrO = null;\n    if (bL.marker.numKeys > 0) {\n        var acmp = 'zzzzzzzzzzzzzzz_AC';\n        for (var i = 1; i <= bL.marker.numKeys; i++) {\n            var m = bL.marker.key(i);\n            var p = m.parameters;\n            if (p.hasOwnProperty(acmp + 'MarkerEnabled') && p.hasOwnProperty(acmp + 'MarkerType') && p.hasOwnProperty(acmp + 'MarkerAppPresetType')) {\n                if (p[acmp + 'MarkerEnabled'] != '1') {\n                    continue;\n                }\n                switch (p[acmp + 'MarkerAppPresetType']) {\n                case '1': {\n                        tTrI = m.time;\n                        break;\n                    }\n                }\n            }\n        }\n    }\n    ;\n    function acPD(fxN) {\n        try {\n            if (bL.effect(fxN).active === false) {\n                ac.en = false;\n            }\n        } catch (e) {\n        }\n    }\n    function acPointValP(fxN, stN, dV) {\n        try {\n            return bL.effect(fxN)(stN);\n        } catch (e) {\n            return dV;\n        }\n    }\n    function acValAdd(val) {\n        acAccA = $bm_sum(acAccA, val);\n    }\n    function easeInCubic(t) {\n        return $bm_mul($bm_mul(t, t), t);\n    }\n    function upACo(tIn, dIn, tOut, dOut, eFi, eFo) {\n        if (dIn < 0) {\n            dIn = 0;\n        }\n        if (dOut < 0) {\n            dOut = 0;\n        }\n        ac.fade = 1;\n        if (t < tOut) {\n            if (t < $bm_sum(tIn, dIn)) {\n                if (dIn == 0) {\n                    ac.fade = 0;\n                } else {\n                    ac.fade = $bm_div($bm_sub(t, tIn), dIn);\n                    if (ac.fade < 0) {\n                        ac.fade = 0;\n                    }\n                    if (ac.fade > 1) {\n                        ac.fade = 1;\n                    }\n                    if (eFi) {\n                        ac.fade = eFi(ac.fade);\n                    }\n                }\n            }\n        } else {\n            if (dOut == 0) {\n                ac.fade = 0;\n            } else {\n                ac.fade = $bm_div($bm_sub(t, tOut), dOut);\n                if (ac.fade < 0) {\n                    ac.fade = 0;\n                }\n                if (ac.fade > 1) {\n                    ac.fade = 1;\n                }\n                if (eFo) {\n                    ac.fade = eFo(ac.fade);\n                }\n                ac.fade = $bm_sub(1, ac.fade);\n            }\n        }\n        ac.intensity = 1;\n        ac.en = true;\n        ac.t = $bm_sub(t, tIn);\n    }\n    var ac = {};\n    ac.en = false;\n    var v = thisProperty.value;\n    var t = time;\n    var acAccA = 0;\n    ac.en = false;\n    if (tTrI !== null && t < tTrI) {\n        upACo(bL.inPoint, $bm_sub(tTrI, bL.inPoint), bL.outPoint, 0);\n        ac.fade = $bm_sub(1, ac.fade);\n    }\n    acPD('AC IN [XUT] Controls');\n    if (ac.en) {\n        acValAdd($bm_mul(acPointValP('AC IN [XUT] Controls', 'Position', [\n            0,\n            200\n        ]), easeInCubic(ac.fade)));\n    }\n    v = thisProperty.value;\n    v = $bm_sum(v, acAccA);\n    return v;\n}\n$bm_rt = result;","l":2},"a":{"a":0,"k":[73,16,0],"ix":1,"l":2},"s":{"a":0,"k":[100,100,100],"ix":6,"l":2}},"ao":0,"ef":[{"ty":5,"nm":"AC IN [XUT] Controls","np":3,"mn":"Pseudo/MHAC PrCtrl XUT 3","ix":1,"en":1,"ef":[{"ty":3,"nm":"Position","mn":"Pseudo/MHAC PrCtrl XUT 3-0001","ix":1,"v":{"a":0,"k":[0,60],"ix":1}}]}],"ip":62.0000025253118,"op":150.000006109625,"st":8.00000032584668,"bm":0},{"ddd":0,"ind":4,"ty":2,"nm":"testStep-1-@2x.png","cl":"png","refId":"image_3","sr":1,"ks":{"o":{"a":0,"k":100,"ix":11,"x":"var $bm_rt;\nvar result;\nresult = getAnimationComposerPresetValue();\nfunction getAnimationComposerPresetValue() {\n    var bL = thisLayer;\n    var tTrI = null;\n    var tTrO = null;\n    if (bL.marker.numKeys > 0) {\n        var acmp = 'zzzzzzzzzzzzzzz_AC';\n        for (var i = 1; i <= bL.marker.numKeys; i++) {\n            var m = bL.marker.key(i);\n            var p = m.parameters;\n            if (p.hasOwnProperty(acmp + 'MarkerEnabled') && p.hasOwnProperty(acmp + 'MarkerType') && p.hasOwnProperty(acmp + 'MarkerAppPresetType')) {\n                if (p[acmp + 'MarkerEnabled'] != '1') {\n                    continue;\n                }\n                switch (p[acmp + 'MarkerAppPresetType']) {\n                case '1': {\n                        tTrI = m.time;\n                        break;\n                    }\n                }\n            }\n        }\n    }\n    ;\n    function acPD(fxN) {\n        try {\n            if (bL.effect(fxN).active === false) {\n                ac.en = false;\n            }\n        } catch (e) {\n        }\n    }\n    function acValMul(val) {\n        acAccM *= val;\n    }\n    function easeInQuint(t) {\n        return $bm_mul($bm_mul($bm_mul($bm_mul(t, t), t), t), t);\n    }\n    function upACo(tIn, dIn, tOut, dOut, eFi, eFo) {\n        if (dIn < 0) {\n            dIn = 0;\n        }\n        if (dOut < 0) {\n            dOut = 0;\n        }\n        ac.fade = 1;\n        if (t < tOut) {\n            if (t < $bm_sum(tIn, dIn)) {\n                if (dIn == 0) {\n                    ac.fade = 0;\n                } else {\n                    ac.fade = $bm_div($bm_sub(t, tIn), dIn);\n                    if (ac.fade < 0) {\n                        ac.fade = 0;\n                    }\n                    if (ac.fade > 1) {\n                        ac.fade = 1;\n                    }\n                    if (eFi) {\n                        ac.fade = eFi(ac.fade);\n                    }\n                }\n            }\n        } else {\n            if (dOut == 0) {\n                ac.fade = 0;\n            } else {\n                ac.fade = $bm_div($bm_sub(t, tOut), dOut);\n                if (ac.fade < 0) {\n                    ac.fade = 0;\n                }\n                if (ac.fade > 1) {\n                    ac.fade = 1;\n                }\n                if (eFo) {\n                    ac.fade = eFo(ac.fade);\n                }\n                ac.fade = $bm_sub(1, ac.fade);\n            }\n        }\n        ac.intensity = 1;\n        ac.en = true;\n        ac.t = $bm_sub(t, tIn);\n    }\n    var ac = {};\n    ac.en = false;\n    var v = thisProperty.value;\n    var t = time;\n    var acAccM = 1;\n    ac.en = false;\n    if (tTrI !== null && t < tTrI) {\n        upACo(bL.inPoint, $bm_sub(tTrI, bL.inPoint), bL.outPoint, 0);\n        ac.fade = $bm_sub(1, ac.fade);\n    }\n    acPD('AC IN [XUT] Controls');\n    if (ac.en) {\n        acValMul($bm_sub(1, easeInQuint(ac.fade)));\n    }\n    v = thisProperty.value;\n    v *= acAccM;\n    return v;\n}\n$bm_rt = result;"},"r":{"a":0,"k":0,"ix":10},"p":{"a":0,"k":[551,1014,0],"ix":2,"x":"var $bm_rt;\nvar result;\nresult = getAnimationComposerPresetValue();\nfunction getAnimationComposerPresetValue() {\n    var bL = thisLayer;\n    var tTrI = null;\n    var tTrO = null;\n    if (bL.marker.numKeys > 0) {\n        var acmp = 'zzzzzzzzzzzzzzz_AC';\n        for (var i = 1; i <= bL.marker.numKeys; i++) {\n            var m = bL.marker.key(i);\n            var p = m.parameters;\n            if (p.hasOwnProperty(acmp + 'MarkerEnabled') && p.hasOwnProperty(acmp + 'MarkerType') && p.hasOwnProperty(acmp + 'MarkerAppPresetType')) {\n                if (p[acmp + 'MarkerEnabled'] != '1') {\n                    continue;\n                }\n                switch (p[acmp + 'MarkerAppPresetType']) {\n                case '1': {\n                        tTrI = m.time;\n                        break;\n                    }\n                }\n            }\n        }\n    }\n    ;\n    function acPD(fxN) {\n        try {\n            if (bL.effect(fxN).active === false) {\n                ac.en = false;\n            }\n        } catch (e) {\n        }\n    }\n    function acPointValP(fxN, stN, dV) {\n        try {\n            return bL.effect(fxN)(stN);\n        } catch (e) {\n            return dV;\n        }\n    }\n    function acValAdd(val) {\n        acAccA = $bm_sum(acAccA, val);\n    }\n    function easeInCubic(t) {\n        return $bm_mul($bm_mul(t, t), t);\n    }\n    function upACo(tIn, dIn, tOut, dOut, eFi, eFo) {\n        if (dIn < 0) {\n            dIn = 0;\n        }\n        if (dOut < 0) {\n            dOut = 0;\n        }\n        ac.fade = 1;\n        if (t < tOut) {\n            if (t < $bm_sum(tIn, dIn)) {\n                if (dIn == 0) {\n                    ac.fade = 0;\n                } else {\n                    ac.fade = $bm_div($bm_sub(t, tIn), dIn);\n                    if (ac.fade < 0) {\n                        ac.fade = 0;\n                    }\n                    if (ac.fade > 1) {\n                        ac.fade = 1;\n                    }\n                    if (eFi) {\n                        ac.fade = eFi(ac.fade);\n                    }\n                }\n            }\n        } else {\n            if (dOut == 0) {\n                ac.fade = 0;\n            } else {\n                ac.fade = $bm_div($bm_sub(t, tOut), dOut);\n                if (ac.fade < 0) {\n                    ac.fade = 0;\n                }\n                if (ac.fade > 1) {\n                    ac.fade = 1;\n                }\n                if (eFo) {\n                    ac.fade = eFo(ac.fade);\n                }\n                ac.fade = $bm_sub(1, ac.fade);\n            }\n        }\n        ac.intensity = 1;\n        ac.en = true;\n        ac.t = $bm_sub(t, tIn);\n    }\n    var ac = {};\n    ac.en = false;\n    var v = thisProperty.value;\n    var t = time;\n    var acAccA = 0;\n    ac.en = false;\n    if (tTrI !== null && t < tTrI) {\n        upACo(bL.inPoint, $bm_sub(tTrI, bL.inPoint), bL.outPoint, 0);\n        ac.fade = $bm_sub(1, ac.fade);\n    }\n    acPD('AC IN [XUT] Controls');\n    if (ac.en) {\n        acValAdd($bm_mul(acPointValP('AC IN [XUT] Controls', 'Position', [\n            0,\n            200\n        ]), easeInCubic(ac.fade)));\n    }\n    v = thisProperty.value;\n    v = $bm_sum(v, acAccA);\n    return v;\n}\n$bm_rt = result;","l":2},"a":{"a":0,"k":[53,16,0],"ix":1,"l":2},"s":{"a":0,"k":[100,100,100],"ix":6,"l":2}},"ao":0,"ef":[{"ty":5,"nm":"AC IN [XUT] Controls","np":3,"mn":"Pseudo/MHAC PrCtrl XUT 3","ix":1,"en":1,"ef":[{"ty":3,"nm":"Position","mn":"Pseudo/MHAC PrCtrl XUT 3-0001","ix":1,"v":{"a":0,"k":[0,60],"ix":1}}]}],"ip":54.0000021994651,"op":150.000006109625,"st":0,"bm":0},{"ddd":0,"ind":5,"ty":2,"nm":"icn-arrowDown.ai","cl":"ai","refId":"image_4","sr":1,"ks":{"o":{"a":0,"k":100,"ix":11,"x":"var $bm_rt;\nvar result;\nresult = getAnimationComposerPresetValue();\nfunction getAnimationComposerPresetValue() {\n    var bL = thisLayer;\n    var tTrI = null;\n    var tTrO = null;\n    if (bL.marker.numKeys > 0) {\n        var acmp = 'zzzzzzzzzzzzzzz_AC';\n        for (var i = 1; i <= bL.marker.numKeys; i++) {\n            var m = bL.marker.key(i);\n            var p = m.parameters;\n            if (p.hasOwnProperty(acmp + 'MarkerEnabled') && p.hasOwnProperty(acmp + 'MarkerType') && p.hasOwnProperty(acmp + 'MarkerAppPresetType')) {\n                if (p[acmp + 'MarkerEnabled'] != '1') {\n                    continue;\n                }\n                switch (p[acmp + 'MarkerAppPresetType']) {\n                case '1': {\n                        tTrI = m.time;\n                        break;\n                    }\n                }\n            }\n        }\n    }\n    ;\n    function acPD(fxN) {\n        try {\n            if (bL.effect(fxN).active === false) {\n                ac.en = false;\n            }\n        } catch (e) {\n        }\n    }\n    function acValMul(val) {\n        acAccM *= val;\n    }\n    function easeInOutCubic(t) {\n        return t < 0.5 ? 4 * t * t * t : (t - 1) * (2 * t - 2) * (2 * t - 2) + 1;\n    }\n    function upACo(tIn, dIn, tOut, dOut, eFi, eFo) {\n        if (dIn < 0) {\n            dIn = 0;\n        }\n        if (dOut < 0) {\n            dOut = 0;\n        }\n        ac.fade = 1;\n        if (t < tOut) {\n            if (t < $bm_sum(tIn, dIn)) {\n                if (dIn == 0) {\n                    ac.fade = 0;\n                } else {\n                    ac.fade = $bm_div($bm_sub(t, tIn), dIn);\n                    if (ac.fade < 0) {\n                        ac.fade = 0;\n                    }\n                    if (ac.fade > 1) {\n                        ac.fade = 1;\n                    }\n                    if (eFi) {\n                        ac.fade = eFi(ac.fade);\n                    }\n                }\n            }\n        } else {\n            if (dOut == 0) {\n                ac.fade = 0;\n            } else {\n                ac.fade = $bm_div($bm_sub(t, tOut), dOut);\n                if (ac.fade < 0) {\n                    ac.fade = 0;\n                }\n                if (ac.fade > 1) {\n                    ac.fade = 1;\n                }\n                if (eFo) {\n                    ac.fade = eFo(ac.fade);\n                }\n                ac.fade = $bm_sub(1, ac.fade);\n            }\n        }\n        ac.intensity = 1;\n        ac.en = true;\n        ac.t = $bm_sub(t, tIn);\n    }\n    var ac = {};\n    ac.en = false;\n    var v = thisProperty.value;\n    var t = time;\n    var acAccM = 1;\n    ac.en = false;\n    if (tTrI !== null && t < tTrI) {\n        upACo(bL.inPoint, $bm_sub(tTrI, bL.inPoint), bL.outPoint, 0);\n        ac.fade = $bm_sub(1, ac.fade);\n    }\n    acPD('AC IN [QJG] Controls');\n    if (ac.en) {\n        acValMul($bm_sub(1, easeInOutCubic(ac.fade)));\n    }\n    v = thisProperty.value;\n    v *= acAccM;\n    return v;\n}\n$bm_rt = result;"},"r":{"a":0,"k":-90,"ix":10},"p":{"a":0,"k":[474,1044.25,0],"ix":2,"l":2},"a":{"a":0,"k":[11,10,0],"ix":1,"l":2},"s":{"a":0,"k":[100,100,100],"ix":6,"x":"var $bm_rt;\nvar result;\nresult = getAnimationComposerPresetValue();\nfunction getAnimationComposerPresetValue() {\n    var bL = thisLayer;\n    var tTrI = null;\n    var tTrO = null;\n    if (bL.marker.numKeys > 0) {\n        var acmp = 'zzzzzzzzzzzzzzz_AC';\n        for (var i = 1; i <= bL.marker.numKeys; i++) {\n            var m = bL.marker.key(i);\n            var p = m.parameters;\n            if (p.hasOwnProperty(acmp + 'MarkerEnabled') && p.hasOwnProperty(acmp + 'MarkerType') && p.hasOwnProperty(acmp + 'MarkerAppPresetType')) {\n                if (p[acmp + 'MarkerEnabled'] != '1') {\n                    continue;\n                }\n                switch (p[acmp + 'MarkerAppPresetType']) {\n                case '1': {\n                        tTrI = m.time;\n                        break;\n                    }\n                }\n            }\n        }\n    }\n    ;\n    function acPD(fxN) {\n        try {\n            if (bL.effect(fxN).active === false) {\n                ac.en = false;\n            }\n        } catch (e) {\n        }\n    }\n    function acSliderValP(fxN, stN, dV) {\n        try {\n            return bL.effect(fxN)(stN);\n        } catch (e) {\n            return dV;\n        }\n    }\n    function acValMul(val) {\n        acAccM *= val;\n    }\n    function easeInOutCubic(t) {\n        return t < 0.5 ? 4 * t * t * t : (t - 1) * (2 * t - 2) * (2 * t - 2) + 1;\n    }\n    function upACo(tIn, dIn, tOut, dOut, eFi, eFo) {\n        if (dIn < 0) {\n            dIn = 0;\n        }\n        if (dOut < 0) {\n            dOut = 0;\n        }\n        ac.fade = 1;\n        if (t < tOut) {\n            if (t < $bm_sum(tIn, dIn)) {\n                if (dIn == 0) {\n                    ac.fade = 0;\n                } else {\n                    ac.fade = $bm_div($bm_sub(t, tIn), dIn);\n                    if (ac.fade < 0) {\n                        ac.fade = 0;\n                    }\n                    if (ac.fade > 1) {\n                        ac.fade = 1;\n                    }\n                    if (eFi) {\n                        ac.fade = eFi(ac.fade);\n                    }\n                }\n            }\n        } else {\n            if (dOut == 0) {\n                ac.fade = 0;\n            } else {\n                ac.fade = $bm_div($bm_sub(t, tOut), dOut);\n                if (ac.fade < 0) {\n                    ac.fade = 0;\n                }\n                if (ac.fade > 1) {\n                    ac.fade = 1;\n                }\n                if (eFo) {\n                    ac.fade = eFo(ac.fade);\n                }\n                ac.fade = $bm_sub(1, ac.fade);\n            }\n        }\n        ac.intensity = 1;\n        ac.en = true;\n        ac.t = $bm_sub(t, tIn);\n    }\n    var ac = {};\n    ac.en = false;\n    var v = thisProperty.value;\n    var t = time;\n    var acAccM = 1;\n    ac.en = false;\n    if (tTrI !== null && t < tTrI) {\n        upACo(bL.inPoint, $bm_sub(tTrI, bL.inPoint), bL.outPoint, 0);\n        ac.fade = $bm_sub(1, ac.fade);\n    }\n    acPD('AC IN [QJG] Controls');\n    if (ac.en) {\n        var startAt = $bm_div(acSliderValP('AC IN [QJG] Controls', 'Size', 30), 100);\n        acValMul($bm_sum(startAt, $bm_mul($bm_sub(1, startAt), $bm_sub(1, easeInOutCubic(ac.fade)))));\n    }\n    v = thisProperty.value;\n    v *= acAccM;\n    return v;\n}\n$bm_rt = result;","l":2}},"ao":0,"ef":[{"ty":5,"nm":"AC IN [QJG] Controls","np":3,"mn":"Pseudo/MHAC PrCtrl QJG 3","ix":1,"en":1,"ef":[{"ty":0,"nm":"Size","mn":"Pseudo/MHAC PrCtrl QJG 3-0001","ix":1,"v":{"a":0,"k":30,"ix":1}}]}],"ip":48.0000019550801,"op":150.000006109625,"st":0,"bm":0},{"ddd":0,"ind":6,"ty":4,"nm":"curveLine-2 Outlines","sr":1,"ks":{"o":{"a":0,"k":100,"ix":11},"r":{"a":0,"k":-90,"ix":10},"p":{"a":0,"k":[439.5,1043.5,0],"ix":2,"l":2},"a":{"a":0,"k":[2.5,34,0],"ix":1,"l":2},"s":{"a":0,"k":[100,100,100],"ix":6,"l":2}},"ao":0,"shapes":[{"ty":"gr","it":[{"ind":0,"ty":"sh","ix":1,"ks":{"a":0,"k":{"i":[[0,0],[0,0]],"o":[[0,0],[0,0]],"v":[[2.258,1.364],[2.258,66.275]],"c":false},"ix":2},"nm":"Path 1","mn":"ADBE Vector Shape - Group","hd":false},{"ty":"st","c":{"a":0,"k":[0.023999999551,0.046999998654,0.231000010173,1],"ix":3},"o":{"a":0,"k":100,"ix":4},"w":{"a":0,"k":3,"ix":5},"lc":1,"lj":1,"ml":10,"bm":0,"nm":"Stroke 1","mn":"ADBE Vector Graphic - Stroke","hd":false},{"ty":"tr","p":{"a":0,"k":[0,0],"ix":2},"a":{"a":0,"k":[0,0],"ix":1},"s":{"a":0,"k":[100,100],"ix":3},"r":{"a":0,"k":0,"ix":6},"o":{"a":0,"k":100,"ix":7},"sk":{"a":0,"k":0,"ix":4},"sa":{"a":0,"k":0,"ix":5},"nm":"Transform"}],"nm":"Group 1","np":2,"cix":2,"bm":0,"ix":1,"mn":"ADBE Vector Group","hd":false},{"ty":"tm","s":{"a":1,"k":[{"i":{"x":[0.833],"y":[0.833]},"o":{"x":[0.167],"y":[0.167]},"t":39,"s":[0]},{"t":48.0000019550801,"s":[100]}],"ix":1},"e":{"a":0,"k":0,"ix":2},"o":{"a":0,"k":0,"ix":3},"m":1,"ix":2,"nm":"Trim Paths 1","mn":"ADBE Vector Filter - Trim","hd":false}],"ip":39.0000015885026,"op":150.000006109625,"st":-21.0000008553475,"bm":0},{"ddd":0,"ind":7,"ty":5,"nm":"INCREASE  PRODUCTIVITY & GAIN INSIGHTS","sr":1,"ks":{"o":{"a":0,"k":100,"ix":11,"x":"var $bm_rt;\nvar result;\nresult = getAnimationComposerPresetValue();\nfunction getAnimationComposerPresetValue() {\n    var bL = thisLayer;\n    var tTrI = null;\n    var tTrO = null;\n    if (bL.marker.numKeys > 0) {\n        var acmp = 'zzzzzzzzzzzzzzz_AC';\n        for (var i = 1; i <= bL.marker.numKeys; i++) {\n            var m = bL.marker.key(i);\n            var p = m.parameters;\n            if (p.hasOwnProperty(acmp + 'MarkerEnabled') && p.hasOwnProperty(acmp + 'MarkerType') && p.hasOwnProperty(acmp + 'MarkerAppPresetType')) {\n                if (p[acmp + 'MarkerEnabled'] != '1') {\n                    continue;\n                }\n                switch (p[acmp + 'MarkerAppPresetType']) {\n                case '1': {\n                        tTrI = m.time;\n                        break;\n                    }\n                }\n            }\n        }\n    }\n    ;\n    function acPD(fxN) {\n        try {\n            if (bL.effect(fxN).active === false) {\n                ac.en = false;\n            }\n        } catch (e) {\n        }\n    }\n    function acValMul(val) {\n        acAccM *= val;\n    }\n    function easeInQuint(t) {\n        return $bm_mul($bm_mul($bm_mul($bm_mul(t, t), t), t), t);\n    }\n    function upACo(tIn, dIn, tOut, dOut, eFi, eFo) {\n        if (dIn < 0) {\n            dIn = 0;\n        }\n        if (dOut < 0) {\n            dOut = 0;\n        }\n        ac.fade = 1;\n        if (t < tOut) {\n            if (t < $bm_sum(tIn, dIn)) {\n                if (dIn == 0) {\n                    ac.fade = 0;\n                } else {\n                    ac.fade = $bm_div($bm_sub(t, tIn), dIn);\n                    if (ac.fade < 0) {\n                        ac.fade = 0;\n                    }\n                    if (ac.fade > 1) {\n                        ac.fade = 1;\n                    }\n                    if (eFi) {\n                        ac.fade = eFi(ac.fade);\n                    }\n                }\n            }\n        } else {\n            if (dOut == 0) {\n                ac.fade = 0;\n            } else {\n                ac.fade = $bm_div($bm_sub(t, tOut), dOut);\n                if (ac.fade < 0) {\n                    ac.fade = 0;\n                }\n                if (ac.fade > 1) {\n                    ac.fade = 1;\n                }\n                if (eFo) {\n                    ac.fade = eFo(ac.fade);\n                }\n                ac.fade = $bm_sub(1, ac.fade);\n            }\n        }\n        ac.intensity = 1;\n        ac.en = true;\n        ac.t = $bm_sub(t, tIn);\n    }\n    var ac = {};\n    ac.en = false;\n    var v = thisProperty.value;\n    var t = time;\n    var acAccM = 1;\n    ac.en = false;\n    if (tTrI !== null && t < tTrI) {\n        upACo(bL.inPoint, $bm_sub(tTrI, bL.inPoint), bL.outPoint, 0);\n        ac.fade = $bm_sub(1, ac.fade);\n    }\n    acPD('AC IN [PDB] Controls');\n    if (ac.en) {\n        acValMul($bm_sub(1, easeInQuint(ac.fade)));\n    }\n    v = thisProperty.value;\n    v *= acAccM;\n    return v;\n}\n$bm_rt = result;"},"r":{"a":0,"k":0,"ix":10},"p":{"a":0,"k":[328,1030,0],"ix":2,"l":2},"a":{"a":0,"k":[0,0,0],"ix":1,"l":2},"s":{"a":0,"k":[100,100,100],"ix":6,"x":"var $bm_rt;\nvar result;\nresult = getAnimationComposerPresetValue();\nfunction getAnimationComposerPresetValue() {\n    var bL = thisLayer;\n    var tTrI = null;\n    var tTrO = null;\n    if (bL.marker.numKeys > 0) {\n        var acmp = 'zzzzzzzzzzzzzzz_AC';\n        for (var i = 1; i <= bL.marker.numKeys; i++) {\n            var m = bL.marker.key(i);\n            var p = m.parameters;\n            if (p.hasOwnProperty(acmp + 'MarkerEnabled') && p.hasOwnProperty(acmp + 'MarkerType') && p.hasOwnProperty(acmp + 'MarkerAppPresetType')) {\n                if (p[acmp + 'MarkerEnabled'] != '1') {\n                    continue;\n                }\n                switch (p[acmp + 'MarkerAppPresetType']) {\n                case '1': {\n                        tTrI = m.time;\n                        break;\n                    }\n                }\n            }\n        }\n    }\n    ;\n    function acPD(fxN) {\n        try {\n            if (bL.effect(fxN).active === false) {\n                ac.en = false;\n            }\n        } catch (e) {\n        }\n    }\n    function acSliderValP(fxN, stN, dV) {\n        try {\n            return bL.effect(fxN)(stN);\n        } catch (e) {\n            return dV;\n        }\n    }\n    function acValMul(val) {\n        acAccM *= val;\n    }\n    function mhOvershoot(t, a, f, d) {\n        if (d <= 0) {\n            d = 0;\n        }\n        var y = $bm_div($bm_mul(a, Math.cos($bm_mul($bm_mul($bm_mul(t, f), Math.PI), 2))), Math.exp($bm_mul(t, d)));\n        if (t < 0.8) {\n            return y;\n        }\n        return $bm_mul(y, $bm_sub(1, $bm_div($bm_sub(t, 0.8), 0.2)));\n    }\n    function upACo(tIn, dIn, tOut, dOut, eFi, eFo) {\n        if (dIn < 0) {\n            dIn = 0;\n        }\n        if (dOut < 0) {\n            dOut = 0;\n        }\n        ac.fade = 1;\n        if (t < tOut) {\n            if (t < $bm_sum(tIn, dIn)) {\n                if (dIn == 0) {\n                    ac.fade = 0;\n                } else {\n                    ac.fade = $bm_div($bm_sub(t, tIn), dIn);\n                    if (ac.fade < 0) {\n                        ac.fade = 0;\n                    }\n                    if (ac.fade > 1) {\n                        ac.fade = 1;\n                    }\n                    if (eFi) {\n                        ac.fade = eFi(ac.fade);\n                    }\n                }\n            }\n        } else {\n            if (dOut == 0) {\n                ac.fade = 0;\n            } else {\n                ac.fade = $bm_div($bm_sub(t, tOut), dOut);\n                if (ac.fade < 0) {\n                    ac.fade = 0;\n                }\n                if (ac.fade > 1) {\n                    ac.fade = 1;\n                }\n                if (eFo) {\n                    ac.fade = eFo(ac.fade);\n                }\n                ac.fade = $bm_sub(1, ac.fade);\n            }\n        }\n        ac.intensity = 1;\n        ac.en = true;\n        ac.t = $bm_sub(t, tIn);\n    }\n    var ac = {};\n    ac.en = false;\n    var v = thisProperty.value;\n    var t = time;\n    var acAccM = 1;\n    ac.en = false;\n    if (tTrI !== null && t < tTrI) {\n        upACo(bL.inPoint, $bm_sub(tTrI, bL.inPoint), bL.outPoint, 0);\n        ac.fade = $bm_sub(1, ac.fade);\n    }\n    acPD('AC IN [PDB] Controls');\n    if (ac.en) {\n        var startAt = $bm_div(acSliderValP('AC IN [PDB] Controls', 'Size', 30), 100);\n        acValMul($bm_sum(startAt, $bm_mul($bm_sub(1, startAt), $bm_sub(1, mhOvershoot($bm_sub(1, ac.fade), 1, acSliderValP('AC IN [PDB] Controls', 'Bounces', 3), 7)))));\n    }\n    v = thisProperty.value;\n    v *= acAccM;\n    return v;\n}\n$bm_rt = result;","l":2}},"ao":0,"ef":[{"ty":5,"nm":"AC IN [PDB] Controls","np":4,"mn":"Pseudo/MHAC PrCtrl PDB 3","ix":1,"en":1,"ef":[{"ty":0,"nm":"Size","mn":"Pseudo/MHAC PrCtrl PDB 3-0001","ix":1,"v":{"a":0,"k":30,"ix":1}},{"ty":0,"nm":"Bounces","mn":"Pseudo/MHAC PrCtrl PDB 3-0002","ix":2,"v":{"a":0,"k":3,"ix":2}}]}],"t":{"d":{"k":[{"s":{"s":16,"f":"NotoSansTC-Bold","t":"INCREASE \rPRODUCTIVITY &\rGAIN INSIGHTS","j":2,"tr":0,"lh":24,"ls":0,"fc":[0.024,0.047,0.231]},"t":0}]},"p":{},"m":{"g":1,"a":{"a":0,"k":[0,0],"ix":2}},"a":[]},"ip":34.0000013848484,"op":150.000006109625,"st":0,"bm":0},{"ddd":0,"ind":8,"ty":4,"nm":"curveLine-1 Outlines","sr":1,"ks":{"o":{"a":0,"k":100,"ix":11},"r":{"a":0,"k":-90,"ix":10},"p":{"a":0,"k":[196,968,0],"ix":2,"l":2},"a":{"a":0,"k":[80.5,51.5,0],"ix":1,"l":2},"s":{"a":0,"k":[100,100,100],"ix":6,"l":2}},"ao":0,"shapes":[{"ty":"gr","it":[{"ind":0,"ty":"sh","ix":1,"ks":{"a":0,"k":{"i":[[0,0],[0,0],[-33,0],[0,0]],"o":[[0,0],[0,-33.001],[0,0],[0,0]],"v":[[-76.773,48.227],[-76.773,11.775],[-16.773,-48.227],[76.773,-48.227]],"c":false},"ix":2},"nm":"Path 1","mn":"ADBE Vector Shape - Group","hd":false},{"ty":"st","c":{"a":0,"k":[0.023999999551,0.046999998654,0.231000010173,1],"ix":3},"o":{"a":0,"k":100,"ix":4},"w":{"a":0,"k":3,"ix":5},"lc":1,"lj":1,"ml":10,"bm":0,"nm":"Stroke 1","mn":"ADBE Vector Graphic - Stroke","hd":false},{"ty":"tr","p":{"a":0,"k":[80.73,52.312],"ix":2},"a":{"a":0,"k":[0,0],"ix":1},"s":{"a":0,"k":[100,100],"ix":3},"r":{"a":0,"k":0,"ix":6},"o":{"a":0,"k":100,"ix":7},"sk":{"a":0,"k":0,"ix":4},"sa":{"a":0,"k":0,"ix":5},"nm":"Transform"}],"nm":"Group 1","np":2,"cix":2,"bm":0,"ix":1,"mn":"ADBE Vector Group","hd":false},{"ty":"tm","s":{"a":1,"k":[{"i":{"x":[0.833],"y":[0.833]},"o":{"x":[0.167],"y":[0.167]},"t":25,"s":[100]},{"t":34.0000013848484,"s":[0]}],"ix":1},"e":{"a":0,"k":100,"ix":2},"o":{"a":0,"k":0,"ix":3},"m":1,"ix":2,"nm":"Trim Paths 1","mn":"ADBE Vector Filter - Trim","hd":false}],"ip":24.00000097754,"op":150.000006109625,"st":0,"bm":0},{"ddd":0,"ind":9,"ty":2,"nm":"addl-illo-1-@2x.png","cl":"png","refId":"image_5","sr":1,"ks":{"o":{"a":0,"k":100,"ix":11,"x":"var $bm_rt;\nvar result;\nresult = getAnimationComposerPresetValue();\nfunction getAnimationComposerPresetValue() {\n    var bL = thisLayer;\n    var tTrI = null;\n    var tTrO = null;\n    if (bL.marker.numKeys > 0) {\n        var acmp = 'zzzzzzzzzzzzzzz_AC';\n        for (var i = 1; i <= bL.marker.numKeys; i++) {\n            var m = bL.marker.key(i);\n            var p = m.parameters;\n            if (p.hasOwnProperty(acmp + 'MarkerEnabled') && p.hasOwnProperty(acmp + 'MarkerType') && p.hasOwnProperty(acmp + 'MarkerAppPresetType')) {\n                if (p[acmp + 'MarkerEnabled'] != '1') {\n                    continue;\n                }\n                switch (p[acmp + 'MarkerAppPresetType']) {\n                case '1': {\n                        tTrI = m.time;\n                        break;\n                    }\n                }\n            }\n        }\n    }\n    ;\n    function acPD(fxN) {\n        try {\n            if (bL.effect(fxN).active === false) {\n                ac.en = false;\n            }\n        } catch (e) {\n        }\n    }\n    function acValMul(val) {\n        acAccM *= val;\n    }\n    function easeInQuint(t) {\n        return $bm_mul($bm_mul($bm_mul($bm_mul(t, t), t), t), t);\n    }\n    function upACo(tIn, dIn, tOut, dOut, eFi, eFo) {\n        if (dIn < 0) {\n            dIn = 0;\n        }\n        if (dOut < 0) {\n            dOut = 0;\n        }\n        ac.fade = 1;\n        if (t < tOut) {\n            if (t < $bm_sum(tIn, dIn)) {\n                if (dIn == 0) {\n                    ac.fade = 0;\n                } else {\n                    ac.fade = $bm_div($bm_sub(t, tIn), dIn);\n                    if (ac.fade < 0) {\n                        ac.fade = 0;\n                    }\n                    if (ac.fade > 1) {\n                        ac.fade = 1;\n                    }\n                    if (eFi) {\n                        ac.fade = eFi(ac.fade);\n                    }\n                }\n            }\n        } else {\n            if (dOut == 0) {\n                ac.fade = 0;\n            } else {\n                ac.fade = $bm_div($bm_sub(t, tOut), dOut);\n                if (ac.fade < 0) {\n                    ac.fade = 0;\n                }\n                if (ac.fade > 1) {\n                    ac.fade = 1;\n                }\n                if (eFo) {\n                    ac.fade = eFo(ac.fade);\n                }\n                ac.fade = $bm_sub(1, ac.fade);\n            }\n        }\n        ac.intensity = 1;\n        ac.en = true;\n        ac.t = $bm_sub(t, tIn);\n    }\n    var ac = {};\n    ac.en = false;\n    var v = thisProperty.value;\n    var t = time;\n    var acAccM = 1;\n    ac.en = false;\n    if (tTrI !== null && t < tTrI) {\n        upACo(bL.inPoint, $bm_sub(tTrI, bL.inPoint), bL.outPoint, 0);\n        ac.fade = $bm_sub(1, ac.fade);\n    }\n    acPD('AC IN [XUT] Controls');\n    if (ac.en) {\n        acValMul($bm_sub(1, easeInQuint(ac.fade)));\n    }\n    v = thisProperty.value;\n    v *= acAccM;\n    return v;\n}\n$bm_rt = result;"},"r":{"a":0,"k":0,"ix":10},"p":{"a":0,"k":[274,748,0],"ix":2,"x":"var $bm_rt;\nvar result;\nresult = getAnimationComposerPresetValue();\nfunction getAnimationComposerPresetValue() {\n    var bL = thisLayer;\n    var tTrI = null;\n    var tTrO = null;\n    if (bL.marker.numKeys > 0) {\n        var acmp = 'zzzzzzzzzzzzzzz_AC';\n        for (var i = 1; i <= bL.marker.numKeys; i++) {\n            var m = bL.marker.key(i);\n            var p = m.parameters;\n            if (p.hasOwnProperty(acmp + 'MarkerEnabled') && p.hasOwnProperty(acmp + 'MarkerType') && p.hasOwnProperty(acmp + 'MarkerAppPresetType')) {\n                if (p[acmp + 'MarkerEnabled'] != '1') {\n                    continue;\n                }\n                switch (p[acmp + 'MarkerAppPresetType']) {\n                case '1': {\n                        tTrI = m.time;\n                        break;\n                    }\n                }\n            }\n        }\n    }\n    ;\n    function acPD(fxN) {\n        try {\n            if (bL.effect(fxN).active === false) {\n                ac.en = false;\n            }\n        } catch (e) {\n        }\n    }\n    function acPointValP(fxN, stN, dV) {\n        try {\n            return bL.effect(fxN)(stN);\n        } catch (e) {\n            return dV;\n        }\n    }\n    function acValAdd(val) {\n        acAccA = $bm_sum(acAccA, val);\n    }\n    function easeInCubic(t) {\n        return $bm_mul($bm_mul(t, t), t);\n    }\n    function upACo(tIn, dIn, tOut, dOut, eFi, eFo) {\n        if (dIn < 0) {\n            dIn = 0;\n        }\n        if (dOut < 0) {\n            dOut = 0;\n        }\n        ac.fade = 1;\n        if (t < tOut) {\n            if (t < $bm_sum(tIn, dIn)) {\n                if (dIn == 0) {\n                    ac.fade = 0;\n                } else {\n                    ac.fade = $bm_div($bm_sub(t, tIn), dIn);\n                    if (ac.fade < 0) {\n                        ac.fade = 0;\n                    }\n                    if (ac.fade > 1) {\n                        ac.fade = 1;\n                    }\n                    if (eFi) {\n                        ac.fade = eFi(ac.fade);\n                    }\n                }\n            }\n        } else {\n            if (dOut == 0) {\n                ac.fade = 0;\n            } else {\n                ac.fade = $bm_div($bm_sub(t, tOut), dOut);\n                if (ac.fade < 0) {\n                    ac.fade = 0;\n                }\n                if (ac.fade > 1) {\n                    ac.fade = 1;\n                }\n                if (eFo) {\n                    ac.fade = eFo(ac.fade);\n                }\n                ac.fade = $bm_sub(1, ac.fade);\n            }\n        }\n        ac.intensity = 1;\n        ac.en = true;\n        ac.t = $bm_sub(t, tIn);\n    }\n    var ac = {};\n    ac.en = false;\n    var v = thisProperty.value;\n    var t = time;\n    var acAccA = 0;\n    ac.en = false;\n    if (tTrI !== null && t < tTrI) {\n        upACo(bL.inPoint, $bm_sub(tTrI, bL.inPoint), bL.outPoint, 0);\n        ac.fade = $bm_sub(1, ac.fade);\n    }\n    acPD('AC IN [XUT] Controls');\n    if (ac.en) {\n        acValAdd($bm_mul(acPointValP('AC IN [XUT] Controls', 'Position', [\n            0,\n            200\n        ]), easeInCubic(ac.fade)));\n    }\n    v = thisProperty.value;\n    v = $bm_sum(v, acAccA);\n    return v;\n}\n$bm_rt = result;","l":2},"a":{"a":0,"k":[249,168,0],"ix":1,"l":2},"s":{"a":0,"k":[100,100,100],"ix":6,"l":2}},"ao":0,"ef":[{"ty":5,"nm":"AC IN [XUT] Controls","np":3,"mn":"Pseudo/MHAC PrCtrl XUT 3","ix":1,"en":1,"ef":[{"ty":3,"nm":"Position","mn":"Pseudo/MHAC PrCtrl XUT 3-0001","ix":1,"v":{"a":0,"k":[0,150],"ix":1}}]}],"ip":7.00000028511585,"op":150.000006109625,"st":7.00000028511585,"bm":0},{"ddd":0,"ind":10,"ty":5,"nm":"5.89","cl":"89","parent":28,"sr":1,"ks":{"o":{"a":1,"k":[{"i":{"x":[0.833],"y":[0.833]},"o":{"x":[0.167],"y":[0.167]},"t":0,"s":[0]},{"t":17.0000006924242,"s":[100]}],"ix":11},"r":{"a":0,"k":0,"ix":10},"p":{"a":0,"k":[821,423,0],"ix":2,"l":2},"a":{"a":0,"k":[0,0,0],"ix":1,"l":2},"s":{"a":0,"k":[100,100,100],"ix":6,"l":2}},"ao":0,"ef":[{"ty":5,"nm":"Slider Control","np":3,"mn":"ADBE Slider Control","ix":1,"en":1,"ef":[{"ty":0,"nm":"Slider","mn":"ADBE Slider Control-0001","ix":1,"v":{"a":1,"k":[{"i":{"x":[0.833],"y":[0.833]},"o":{"x":[0.167],"y":[0.167]},"t":0,"s":[5.89]},{"i":{"x":[0.833],"y":[0.833]},"o":{"x":[0.167],"y":[0.167]},"t":69,"s":[5.89]},{"t":149.000006068894,"s":[6.25]}],"ix":1}}]}],"t":{"d":{"x":"var $bm_rt;\n$bm_rt = effect('Slider Control')('Slider').value.toFixed(2);","k":[{"s":{"s":56,"f":"NunitoSans-ExtraBold","t":"5.89","j":0,"tr":0,"lh":67.2,"ls":0,"fc":[0.024,0.047,0.231]},"t":0}]},"p":{},"m":{"g":1,"a":{"a":0,"k":[0,0],"ix":2}},"a":[]},"ip":0,"op":150.000006109625,"st":0,"bm":0},{"ddd":0,"ind":11,"ty":5,"nm":"34","parent":28,"sr":1,"ks":{"o":{"a":1,"k":[{"i":{"x":[0.833],"y":[0.833]},"o":{"x":[0.167],"y":[0.167]},"t":0,"s":[0]},{"t":17.0000006924242,"s":[100]}],"ix":11},"r":{"a":0,"k":0,"ix":10},"p":{"a":0,"k":[564.904,853,0],"ix":2,"l":2},"a":{"a":0,"k":[0,0,0],"ix":1,"l":2},"s":{"a":0,"k":[100,100,100],"ix":6,"l":2}},"ao":0,"ef":[{"ty":5,"nm":"Slider Control","np":3,"mn":"ADBE Slider Control","ix":1,"en":1,"ef":[{"ty":0,"nm":"Slider","mn":"ADBE Slider Control-0001","ix":1,"v":{"a":1,"k":[{"i":{"x":[0.833],"y":[0.833]},"o":{"x":[0.167],"y":[0.167]},"t":0,"s":[34]},{"i":{"x":[0.833],"y":[0.833]},"o":{"x":[0.167],"y":[0.167]},"t":69,"s":[34]},{"t":149.000006068894,"s":[51]}],"ix":1}}]}],"t":{"d":{"x":"var $bm_rt;\n$bm_rt = Math.round(effect('Slider Control')('Slider'));","k":[{"s":{"s":56,"f":"NunitoSans-ExtraBold","t":"34","j":0,"tr":0,"lh":67.2,"ls":0,"fc":[0.024,0.047,0.231]},"t":0}]},"p":{},"m":{"g":1,"a":{"a":0,"k":[0,0],"ix":2}},"a":[]},"ip":0,"op":150.000006109625,"st":0,"bm":0},{"ddd":0,"ind":12,"ty":5,"nm":"16","parent":28,"sr":1,"ks":{"o":{"a":1,"k":[{"i":{"x":[0.833],"y":[0.833]},"o":{"x":[0.167],"y":[0.167]},"t":0,"s":[0]},{"t":17.0000006924242,"s":[100]}],"ix":11},"r":{"a":0,"k":0,"ix":10},"p":{"a":0,"k":[819.656,852,0],"ix":2,"l":2},"a":{"a":0,"k":[0,0,0],"ix":1,"l":2},"s":{"a":0,"k":[100,100,100],"ix":6,"l":2}},"ao":0,"ef":[{"ty":5,"nm":"Slider Control","np":3,"mn":"ADBE Slider Control","ix":1,"en":1,"ef":[{"ty":0,"nm":"Slider","mn":"ADBE Slider Control-0001","ix":1,"v":{"a":1,"k":[{"i":{"x":[0.833],"y":[0.833]},"o":{"x":[0.167],"y":[0.167]},"t":0,"s":[16]},{"i":{"x":[0.833],"y":[0.833]},"o":{"x":[0.167],"y":[0.167]},"t":69,"s":[16]},{"t":149.000006068894,"s":[19]}],"ix":1}}]}],"t":{"d":{"x":"var $bm_rt;\n$bm_rt = Math.round(effect('Slider Control')('Slider'));","k":[{"s":{"s":56,"f":"NunitoSans-ExtraBold","t":"16","j":0,"tr":0,"lh":67.2,"ls":0,"fc":[0.024,0.047,0.231]},"t":0}]},"p":{},"m":{"g":1,"a":{"a":0,"k":[0,0],"ix":2}},"a":[]},"ip":0,"op":150.000006109625,"st":0,"bm":0},{"ddd":0,"ind":13,"ty":5,"nm":"1181","parent":28,"sr":1,"ks":{"o":{"a":1,"k":[{"i":{"x":[0.833],"y":[0.833]},"o":{"x":[0.167],"y":[0.167]},"t":0,"s":[0]},{"t":17.0000006924242,"s":[100]}],"ix":11},"r":{"a":0,"k":0,"ix":10},"p":{"a":0,"k":[819.656,636,0],"ix":2,"l":2},"a":{"a":0,"k":[0,0,0],"ix":1,"l":2},"s":{"a":0,"k":[100,100,100],"ix":6,"l":2}},"ao":0,"ef":[{"ty":5,"nm":"Slider Control","np":3,"mn":"ADBE Slider Control","ix":1,"en":1,"ef":[{"ty":0,"nm":"Slider","mn":"ADBE Slider Control-0001","ix":1,"v":{"a":1,"k":[{"i":{"x":[0.833],"y":[0.833]},"o":{"x":[0.167],"y":[0.167]},"t":0,"s":[38]},{"i":{"x":[0.833],"y":[0.833]},"o":{"x":[0.167],"y":[0.167]},"t":69,"s":[38]},{"t":149.000006068894,"s":[122]}],"ix":1}}]}],"t":{"d":{"x":"var $bm_rt;\n$bm_rt = Math.round(effect('Slider Control')('Slider'));","k":[{"s":{"s":56,"f":"NunitoSans-ExtraBold","t":"1180","j":0,"tr":0,"lh":67.2,"ls":0,"fc":[0.024,0.047,0.231]},"t":0}]},"p":{},"m":{"g":1,"a":{"a":0,"k":[0,0],"ix":2}},"a":[]},"ip":0,"op":150.000006109625,"st":0,"bm":0},{"ddd":0,"ind":14,"ty":5,"nm":"21","parent":28,"sr":1,"ks":{"o":{"a":1,"k":[{"i":{"x":[0.833],"y":[0.833]},"o":{"x":[0.167],"y":[0.167]},"t":0,"s":[0]},{"t":17.0000006924242,"s":[100]}],"ix":11},"r":{"a":0,"k":0,"ix":10},"p":{"a":0,"k":[564.904,637,0],"ix":2,"l":2},"a":{"a":0,"k":[0,0,0],"ix":1,"l":2},"s":{"a":0,"k":[100,100,100],"ix":6,"l":2}},"ao":0,"ef":[{"ty":5,"nm":"Slider Control","np":3,"mn":"ADBE Slider Control","ix":1,"en":1,"ef":[{"ty":0,"nm":"Slider","mn":"ADBE Slider Control-0001","ix":1,"v":{"a":1,"k":[{"i":{"x":[0.833],"y":[0.833]},"o":{"x":[0.167],"y":[0.167]},"t":0,"s":[21]},{"i":{"x":[0.833],"y":[0.833]},"o":{"x":[0.167],"y":[0.167]},"t":69,"s":[21]},{"t":149.000006068894,"s":[27]}],"ix":1}}]}],"t":{"d":{"x":"var $bm_rt;\n$bm_rt = Math.round(effect('Slider Control')('Slider'));","k":[{"s":{"s":56,"f":"NunitoSans-ExtraBold","t":"21","j":0,"tr":0,"lh":67.2,"ls":0,"fc":[0.024,0.047,0.231]},"t":0}]},"p":{},"m":{"g":1,"a":{"a":0,"k":[0,0],"ix":2}},"a":[]},"ip":0,"op":150.000006109625,"st":0,"bm":0},{"ddd":0,"ind":15,"ty":5,"nm":"1180","parent":28,"sr":1,"ks":{"o":{"a":1,"k":[{"i":{"x":[0.833],"y":[0.833]},"o":{"x":[0.167],"y":[0.167]},"t":0,"s":[0]},{"t":17.0000006924242,"s":[100]}],"ix":11},"r":{"a":0,"k":0,"ix":10},"p":{"a":0,"k":[563,423,0],"ix":2,"l":2},"a":{"a":0,"k":[0,0,0],"ix":1,"l":2},"s":{"a":0,"k":[100,100,100],"ix":6,"l":2}},"ao":0,"ef":[{"ty":5,"nm":"Slider Control","np":3,"mn":"ADBE Slider Control","ix":1,"en":1,"ef":[{"ty":0,"nm":"Slider","mn":"ADBE Slider Control-0001","ix":1,"v":{"a":1,"k":[{"i":{"x":[0.833],"y":[0.833]},"o":{"x":[0.167],"y":[0.167]},"t":0,"s":[1180]},{"i":{"x":[0.833],"y":[0.833]},"o":{"x":[0.167],"y":[0.167]},"t":69,"s":[1180]},{"t":149.000006068894,"s":[1183]}],"ix":1}}]}],"t":{"d":{"x":"var $bm_rt;\n$bm_rt = Math.round(effect('Slider Control')('Slider'));","k":[{"s":{"s":56,"f":"NunitoSans-ExtraBold","t":"1180","j":0,"tr":0,"lh":67.2,"ls":0,"fc":[0.024,0.047,0.231]},"t":0}]},"p":{},"m":{"g":1,"a":{"a":0,"k":[0,0],"ix":2}},"a":[]},"ip":0,"op":150.000006109625,"st":0,"bm":0},{"ddd":0,"ind":16,"ty":4,"nm":"shape-chartBar-1","parent":28,"sr":1,"ks":{"o":{"a":1,"k":[{"i":{"x":[0.833],"y":[0.833]},"o":{"x":[0.167],"y":[0.167]},"t":0,"s":[0]},{"t":17.0000006924242,"s":[100]}],"ix":11},"r":{"a":0,"k":0,"ix":10},"p":{"a":0,"k":[1147,635,0],"ix":2,"l":2},"a":{"a":0,"k":[16,211,0],"ix":1,"l":2},"s":{"a":0,"k":[100,100,100],"ix":6,"l":2}},"ao":0,"shapes":[{"ty":"gr","it":[{"ind":0,"ty":"sh","ix":1,"ks":{"a":0,"k":{"i":[[-2.761,0],[0,0],[0,-2.761],[0,0],[2.762,0],[0,0],[0,2.762],[0,0]],"o":[[0,0],[2.762,0],[0,0],[0,2.762],[0,0],[-2.761,0],[0,0],[0,-2.761]],"v":[[-6,-206],[6,-206],[11,-201],[11,201],[6,206],[-6,206],[-11,201],[-11,-201]],"c":true},"ix":2},"nm":"Path 1","mn":"ADBE Vector Shape - Group","hd":false},{"ty":"fl","c":{"a":0,"k":[0,0.819999964097,0.517999985639,1],"ix":4},"o":{"a":0,"k":100,"ix":5},"r":1,"bm":0,"nm":"Fill 1","mn":"ADBE Vector Graphic - Fill","hd":false},{"ty":"tr","p":{"a":0,"k":[16.703,210.799],"ix":2},"a":{"a":0,"k":[0,0],"ix":1},"s":{"a":0,"k":[100,100],"ix":3},"r":{"a":0,"k":0,"ix":6},"o":{"a":0,"k":100,"ix":7},"sk":{"a":0,"k":0,"ix":4},"sa":{"a":0,"k":0,"ix":5},"nm":"Transform"}],"nm":"Group 1","np":2,"cix":2,"bm":0,"ix":1,"mn":"ADBE Vector Group","hd":false}],"ip":0,"op":150.000006109625,"st":0,"bm":0},{"ddd":0,"ind":17,"ty":4,"nm":"shape-chartBar-2","parent":28,"sr":1,"ks":{"o":{"a":1,"k":[{"i":{"x":[0.833],"y":[0.833]},"o":{"x":[0.167],"y":[0.167]},"t":0,"s":[0]},{"t":17.0000006924242,"s":[100]}],"ix":11},"r":{"a":0,"k":0,"ix":10},"p":{"a":0,"k":[1209,635,0],"ix":2,"l":2},"a":{"a":0,"k":[16,211,0],"ix":1,"l":2},"s":{"a":0,"k":[100,100,100],"ix":6,"l":2}},"ao":0,"shapes":[{"ty":"gr","it":[{"ind":0,"ty":"sh","ix":1,"ks":{"a":0,"k":{"i":[[-2.761,0],[0,0],[0,-2.761],[0,0],[2.762,0],[0,0],[0,2.762],[0,0]],"o":[[0,0],[2.762,0],[0,0],[0,2.762],[0,0],[-2.761,0],[0,0],[0,-2.761]],"v":[[-6,-133.5],[6,-133.5],[11,-128.5],[11,201],[6,206],[-6,206],[-11,201],[-11,-128.5]],"c":true},"ix":2},"nm":"Path 1","mn":"ADBE Vector Shape - Group","hd":false},{"ty":"fl","c":{"a":0,"k":[0,0.819999964097,0.517999985639,1],"ix":4},"o":{"a":0,"k":100,"ix":5},"r":1,"bm":0,"nm":"Fill 1","mn":"ADBE Vector Graphic - Fill","hd":false},{"ty":"tr","p":{"a":0,"k":[16.703,210.799],"ix":2},"a":{"a":0,"k":[0,0],"ix":1},"s":{"a":0,"k":[100,100],"ix":3},"r":{"a":0,"k":0,"ix":6},"o":{"a":0,"k":100,"ix":7},"sk":{"a":0,"k":0,"ix":4},"sa":{"a":0,"k":0,"ix":5},"nm":"Transform"}],"nm":"Group 1","np":2,"cix":2,"bm":0,"ix":1,"mn":"ADBE Vector Group","hd":false}],"ip":0,"op":150.000006109625,"st":0,"bm":0},{"ddd":0,"ind":18,"ty":4,"nm":"shape-chartBar-3","parent":28,"sr":1,"ks":{"o":{"a":1,"k":[{"i":{"x":[0.833],"y":[0.833]},"o":{"x":[0.167],"y":[0.167]},"t":0,"s":[0]},{"t":17.0000006924242,"s":[100]}],"ix":11},"r":{"a":0,"k":0,"ix":10},"p":{"a":0,"k":[1271,635,0],"ix":2,"l":2},"a":{"a":0,"k":[16,211,0],"ix":1,"l":2},"s":{"a":0,"k":[100,100,100],"ix":6,"l":2}},"ao":0,"shapes":[{"ty":"gr","it":[{"ind":0,"ty":"sh","ix":1,"ks":{"a":0,"k":{"i":[[-2.761,0],[0,0],[0,-2.761],[0,0],[2.762,0],[0,0],[0,2.762],[0,0]],"o":[[0,0],[2.762,0],[0,0],[0,2.762],[0,0],[-2.761,0],[0,0],[0,-2.761]],"v":[[-6,-147.5],[6,-147.5],[11,-142.5],[11,201],[6,206],[-6,206],[-11,201],[-11,-142.5]],"c":true},"ix":2},"nm":"Path 1","mn":"ADBE Vector Shape - Group","hd":false},{"ty":"fl","c":{"a":0,"k":[0,0.819999964097,0.517999985639,1],"ix":4},"o":{"a":0,"k":100,"ix":5},"r":1,"bm":0,"nm":"Fill 1","mn":"ADBE Vector Graphic - Fill","hd":false},{"ty":"tr","p":{"a":0,"k":[16.703,210.799],"ix":2},"a":{"a":0,"k":[0,0],"ix":1},"s":{"a":0,"k":[100,100],"ix":3},"r":{"a":0,"k":0,"ix":6},"o":{"a":0,"k":100,"ix":7},"sk":{"a":0,"k":0,"ix":4},"sa":{"a":0,"k":0,"ix":5},"nm":"Transform"}],"nm":"Group 1","np":2,"cix":2,"bm":0,"ix":1,"mn":"ADBE Vector Group","hd":false}],"ip":0,"op":150.000006109625,"st":0,"bm":0},{"ddd":0,"ind":19,"ty":4,"nm":"shape-chartBar-4","parent":28,"sr":1,"ks":{"o":{"a":1,"k":[{"i":{"x":[0.833],"y":[0.833]},"o":{"x":[0.167],"y":[0.167]},"t":0,"s":[0]},{"t":17.0000006924242,"s":[100]}],"ix":11},"r":{"a":0,"k":0,"ix":10},"p":{"a":0,"k":[1331,635,0],"ix":2,"l":2},"a":{"a":0,"k":[16,211,0],"ix":1,"l":2},"s":{"a":0,"k":[100,100,100],"ix":6,"l":2}},"ao":0,"shapes":[{"ty":"gr","it":[{"ind":0,"ty":"sh","ix":1,"ks":{"a":0,"k":{"i":[[-2.761,0],[0,0],[0,-2.761],[0,0],[2.762,0],[0,0],[0,2.762],[0,0]],"o":[[0,0],[2.762,0],[0,0],[0,2.762],[0,0],[-2.761,0],[0,0],[0,-2.761]],"v":[[-6,36.5],[6,36.5],[11,41.5],[11,201],[6,206],[-6,206],[-11,201],[-11,41.5]],"c":true},"ix":2},"nm":"Path 1","mn":"ADBE Vector Shape - Group","hd":false},{"ty":"fl","c":{"a":0,"k":[0,0.819999964097,0.517999985639,1],"ix":4},"o":{"a":0,"k":100,"ix":5},"r":1,"bm":0,"nm":"Fill 1","mn":"ADBE Vector Graphic - Fill","hd":false},{"ty":"tr","p":{"a":0,"k":[16.703,210.799],"ix":2},"a":{"a":0,"k":[0,0],"ix":1},"s":{"a":0,"k":[100,100],"ix":3},"r":{"a":0,"k":0,"ix":6},"o":{"a":0,"k":100,"ix":7},"sk":{"a":0,"k":0,"ix":4},"sa":{"a":0,"k":0,"ix":5},"nm":"Transform"}],"nm":"Group 1","np":2,"cix":2,"bm":0,"ix":1,"mn":"ADBE Vector Group","hd":false}],"ip":0,"op":150.000006109625,"st":0,"bm":0},{"ddd":0,"ind":20,"ty":2,"nm":"chart-box-@2x.png","cl":"png","parent":28,"refId":"image_6","sr":1,"ks":{"o":{"a":1,"k":[{"i":{"x":[0.833],"y":[0.833]},"o":{"x":[0.167],"y":[0.167]},"t":0,"s":[0]},{"t":17.0000006924242,"s":[100]}],"ix":11},"r":{"a":0,"k":0,"ix":10},"p":{"a":0,"k":[1238,600,0],"ix":2,"l":2},"a":{"a":0,"k":[178,307,0],"ix":1,"l":2},"s":{"a":0,"k":[100,100,100],"ix":6,"l":2}},"ao":0,"ip":0,"op":150.000006109625,"st":0,"bm":0},{"ddd":0,"ind":21,"ty":2,"nm":"team-box-@2x.png","cl":"png","parent":28,"refId":"image_7","sr":1,"ks":{"o":{"a":1,"k":[{"i":{"x":[0.833],"y":[0.833]},"o":{"x":[0.167],"y":[0.167]},"t":0,"s":[0]},{"t":17.0000006924242,"s":[100]}],"ix":11},"r":{"a":0,"k":0,"ix":10},"p":{"a":0,"k":[980,1028,0],"ix":2,"l":2},"a":{"a":0,"k":[436,93,0],"ix":1,"l":2},"s":{"a":0,"k":[100,100,100],"ix":6,"l":2}},"ao":0,"ip":0,"op":150.000006109625,"st":0,"bm":0},{"ddd":0,"ind":22,"ty":2,"nm":"db-tile-6-@2x.png","cl":"png","parent":28,"refId":"image_8","sr":1,"ks":{"o":{"a":1,"k":[{"i":{"x":[0.833],"y":[0.833]},"o":{"x":[0.167],"y":[0.167]},"t":0,"s":[0]},{"t":17.0000006924242,"s":[100]}],"ix":11},"r":{"a":0,"k":0,"ix":10},"p":{"a":0,"k":[915,814,0],"ix":2,"l":2},"a":{"a":0,"k":[114,93,0],"ix":1,"l":2},"s":{"a":0,"k":[100,100,100],"ix":6,"l":2}},"ao":0,"ip":0,"op":150.000006109625,"st":0,"bm":0},{"ddd":0,"ind":23,"ty":2,"nm":"db-tile-5-@2x.png","cl":"png","parent":28,"refId":"image_9","sr":1,"ks":{"o":{"a":1,"k":[{"i":{"x":[0.833],"y":[0.833]},"o":{"x":[0.167],"y":[0.167]},"t":0,"s":[0]},{"t":17.0000006924242,"s":[100]}],"ix":11},"r":{"a":0,"k":0,"ix":10},"p":{"a":0,"k":[658,814,0],"ix":2,"l":2},"a":{"a":0,"k":[114,93,0],"ix":1,"l":2},"s":{"a":0,"k":[100,100,100],"ix":6,"l":2}},"ao":0,"ip":0,"op":150.000006109625,"st":0,"bm":0},{"ddd":0,"ind":24,"ty":2,"nm":"db-tile-4-@2x.png","cl":"png","parent":28,"refId":"image_10","sr":1,"ks":{"o":{"a":1,"k":[{"i":{"x":[0.833],"y":[0.833]},"o":{"x":[0.167],"y":[0.167]},"t":0,"s":[0]},{"t":17.0000006924242,"s":[100]}],"ix":11},"r":{"a":0,"k":0,"ix":10},"p":{"a":0,"k":[915,600,0],"ix":2,"l":2},"a":{"a":0,"k":[114,93,0],"ix":1,"l":2},"s":{"a":0,"k":[100,100,100],"ix":6,"l":2}},"ao":0,"ip":0,"op":150.000006109625,"st":0,"bm":0},{"ddd":0,"ind":25,"ty":2,"nm":"db-tile-3-@3x.png","cl":"png","parent":28,"refId":"image_11","sr":1,"ks":{"o":{"a":1,"k":[{"i":{"x":[0.833],"y":[0.833]},"o":{"x":[0.167],"y":[0.167]},"t":0,"s":[0]},{"t":17.0000006924242,"s":[100]}],"ix":11},"r":{"a":0,"k":0,"ix":10},"p":{"a":0,"k":[658,600,0],"ix":2,"l":2},"a":{"a":0,"k":[114,93,0],"ix":1,"l":2},"s":{"a":0,"k":[100,100,100],"ix":6,"l":2}},"ao":0,"ip":0,"op":150.000006109625,"st":0,"bm":0},{"ddd":0,"ind":26,"ty":2,"nm":"db-tile-2-@2x.png","cl":"png","parent":28,"refId":"image_12","sr":1,"ks":{"o":{"a":1,"k":[{"i":{"x":[0.833],"y":[0.833]},"o":{"x":[0.167],"y":[0.167]},"t":0,"s":[0]},{"t":17.0000006924242,"s":[100]}],"ix":11},"r":{"a":0,"k":0,"ix":10},"p":{"a":0,"k":[915,386,0],"ix":2,"l":2},"a":{"a":0,"k":[114,93,0],"ix":1,"l":2},"s":{"a":0,"k":[100,100,100],"ix":6,"l":2}},"ao":0,"ip":0,"op":150.000006109625,"st":0,"bm":0},{"ddd":0,"ind":27,"ty":2,"nm":"db-tile-1-@2x.png","cl":"png","parent":28,"refId":"image_13","sr":1,"ks":{"o":{"a":1,"k":[{"i":{"x":[0.833],"y":[0.833]},"o":{"x":[0.167],"y":[0.167]},"t":0,"s":[0]},{"t":17.0000006924242,"s":[100]}],"ix":11},"r":{"a":0,"k":0,"ix":10},"p":{"a":0,"k":[658,386,0],"ix":2,"l":2},"a":{"a":0,"k":[114,93,0],"ix":1,"l":2},"s":{"a":0,"k":[100,100,100],"ix":6,"l":2}},"ao":0,"ip":0,"op":150.000006109625,"st":0,"bm":0},{"ddd":0,"ind":28,"ty":2,"nm":"app-frame-@2x.png","cl":"png","refId":"image_14","sr":1,"ks":{"o":{"a":0,"k":100,"ix":11,"x":"var $bm_rt;\nvar result;\nresult = getAnimationComposerPresetValue();\nfunction getAnimationComposerPresetValue() {\n    var bL = thisLayer;\n    var tTrI = null;\n    var tTrO = null;\n    if (bL.marker.numKeys > 0) {\n        var acmp = 'zzzzzzzzzzzzzzz_AC';\n        for (var i = 1; i <= bL.marker.numKeys; i++) {\n            var m = bL.marker.key(i);\n            var p = m.parameters;\n            if (p.hasOwnProperty(acmp + 'MarkerEnabled') && p.hasOwnProperty(acmp + 'MarkerType') && p.hasOwnProperty(acmp + 'MarkerAppPresetType')) {\n                if (p[acmp + 'MarkerEnabled'] != '1') {\n                    continue;\n                }\n                switch (p[acmp + 'MarkerAppPresetType']) {\n                case '1': {\n                        tTrI = m.time;\n                        break;\n                    }\n                }\n            }\n        }\n    }\n    ;\n    function acPD(fxN) {\n        try {\n            if (bL.effect(fxN).active === false) {\n                ac.en = false;\n            }\n        } catch (e) {\n        }\n    }\n    function acValMul(val) {\n        acAccM *= val;\n    }\n    function easeInQuint(t) {\n        return $bm_mul($bm_mul($bm_mul($bm_mul(t, t), t), t), t);\n    }\n    function upACo(tIn, dIn, tOut, dOut, eFi, eFo) {\n        if (dIn < 0) {\n            dIn = 0;\n        }\n        if (dOut < 0) {\n            dOut = 0;\n        }\n        ac.fade = 1;\n        if (t < tOut) {\n            if (t < $bm_sum(tIn, dIn)) {\n                if (dIn == 0) {\n                    ac.fade = 0;\n                } else {\n                    ac.fade = $bm_div($bm_sub(t, tIn), dIn);\n                    if (ac.fade < 0) {\n                        ac.fade = 0;\n                    }\n                    if (ac.fade > 1) {\n                        ac.fade = 1;\n                    }\n                    if (eFi) {\n                        ac.fade = eFi(ac.fade);\n                    }\n                }\n            }\n        } else {\n            if (dOut == 0) {\n                ac.fade = 0;\n            } else {\n                ac.fade = $bm_div($bm_sub(t, tOut), dOut);\n                if (ac.fade < 0) {\n                    ac.fade = 0;\n                }\n                if (ac.fade > 1) {\n                    ac.fade = 1;\n                }\n                if (eFo) {\n                    ac.fade = eFo(ac.fade);\n                }\n                ac.fade = $bm_sub(1, ac.fade);\n            }\n        }\n        ac.intensity = 1;\n        ac.en = true;\n        ac.t = $bm_sub(t, tIn);\n    }\n    var ac = {};\n    ac.en = false;\n    var v = thisProperty.value;\n    var t = time;\n    var acAccM = 1;\n    ac.en = false;\n    if (tTrI !== null && t < tTrI) {\n        upACo(bL.inPoint, $bm_sub(tTrI, bL.inPoint), bL.outPoint, 0);\n        ac.fade = $bm_sub(1, ac.fade);\n    }\n    acPD('AC IN [XUT] Controls');\n    if (ac.en) {\n        acValMul($bm_sub(1, easeInQuint(ac.fade)));\n    }\n    v = thisProperty.value;\n    v *= acAccM;\n    return v;\n}\n$bm_rt = result;"},"r":{"a":0,"k":0,"ix":10},"p":{"a":0,"k":[976,660,0],"ix":2,"x":"var $bm_rt;\nvar result;\nresult = getAnimationComposerPresetValue();\nfunction getAnimationComposerPresetValue() {\n    var bL = thisLayer;\n    var tTrI = null;\n    var tTrO = null;\n    if (bL.marker.numKeys > 0) {\n        var acmp = 'zzzzzzzzzzzzzzz_AC';\n        for (var i = 1; i <= bL.marker.numKeys; i++) {\n            var m = bL.marker.key(i);\n            var p = m.parameters;\n            if (p.hasOwnProperty(acmp + 'MarkerEnabled') && p.hasOwnProperty(acmp + 'MarkerType') && p.hasOwnProperty(acmp + 'MarkerAppPresetType')) {\n                if (p[acmp + 'MarkerEnabled'] != '1') {\n                    continue;\n                }\n                switch (p[acmp + 'MarkerAppPresetType']) {\n                case '1': {\n                        tTrI = m.time;\n                        break;\n                    }\n                }\n            }\n        }\n    }\n    ;\n    function acPD(fxN) {\n        try {\n            if (bL.effect(fxN).active === false) {\n                ac.en = false;\n            }\n        } catch (e) {\n        }\n    }\n    function acPointValP(fxN, stN, dV) {\n        try {\n            return bL.effect(fxN)(stN);\n        } catch (e) {\n            return dV;\n        }\n    }\n    function acValAdd(val) {\n        acAccA = $bm_sum(acAccA, val);\n    }\n    function easeInCubic(t) {\n        return $bm_mul($bm_mul(t, t), t);\n    }\n    function upACo(tIn, dIn, tOut, dOut, eFi, eFo) {\n        if (dIn < 0) {\n            dIn = 0;\n        }\n        if (dOut < 0) {\n            dOut = 0;\n        }\n        ac.fade = 1;\n        if (t < tOut) {\n            if (t < $bm_sum(tIn, dIn)) {\n                if (dIn == 0) {\n                    ac.fade = 0;\n                } else {\n                    ac.fade = $bm_div($bm_sub(t, tIn), dIn);\n                    if (ac.fade < 0) {\n                        ac.fade = 0;\n                    }\n                    if (ac.fade > 1) {\n                        ac.fade = 1;\n                    }\n                    if (eFi) {\n                        ac.fade = eFi(ac.fade);\n                    }\n                }\n            }\n        } else {\n            if (dOut == 0) {\n                ac.fade = 0;\n            } else {\n                ac.fade = $bm_div($bm_sub(t, tOut), dOut);\n                if (ac.fade < 0) {\n                    ac.fade = 0;\n                }\n                if (ac.fade > 1) {\n                    ac.fade = 1;\n                }\n                if (eFo) {\n                    ac.fade = eFo(ac.fade);\n                }\n                ac.fade = $bm_sub(1, ac.fade);\n            }\n        }\n        ac.intensity = 1;\n        ac.en = true;\n        ac.t = $bm_sub(t, tIn);\n    }\n    var ac = {};\n    ac.en = false;\n    var v = thisProperty.value;\n    var t = time;\n    var acAccA = 0;\n    ac.en = false;\n    if (tTrI !== null && t < tTrI) {\n        upACo(bL.inPoint, $bm_sub(tTrI, bL.inPoint), bL.outPoint, 0);\n        ac.fade = $bm_sub(1, ac.fade);\n    }\n    acPD('AC IN [XUT] Controls');\n    if (ac.en) {\n        acValAdd($bm_mul(acPointValP('AC IN [XUT] Controls', 'Position', [\n            0,\n            200\n        ]), easeInCubic(ac.fade)));\n    }\n    v = thisProperty.value;\n    v = $bm_sum(v, acAccA);\n    return v;\n}\n$bm_rt = result;","l":2},"a":{"a":0,"k":[828,697,0],"ix":1,"l":2},"s":{"a":0,"k":[100,100,100],"ix":6,"l":2}},"ao":0,"ef":[{"ty":5,"nm":"AC IN [XUT] Controls","np":3,"mn":"Pseudo/MHAC PrCtrl XUT 3","ix":1,"en":1,"ef":[{"ty":3,"nm":"Position","mn":"Pseudo/MHAC PrCtrl XUT 3-0001","ix":1,"v":{"a":0,"k":[0,150],"ix":1}}]}],"ip":0,"op":150.000006109625,"st":0,"bm":0}],"markers":[],"chars":[{"ch":"1","size":56,"style":"ExtraBold","w":60,"data":{"shapes":[{"ty":"gr","it":[{"ind":0,"ty":"sh","ix":1,"ks":{"a":0,"k":{"i":[[0,0],[0,0],[0,0],[0,0],[0,0],[0,0],[0,0],[0,0],[0,0],[0,0],[0,0]],"o":[[0,0],[0,0],[0,0],[0,0],[0,0],[0,0],[0,0],[0,0],[0,0],[0,0],[0,0]],"v":[[41.3,-70.5],[30.2,-70.5],[7.8,-57.4],[13.7,-46.2],[25.7,-53.2],[25.7,-12.5],[10.5,-12.5],[10.5,0],[56.5,0],[56.5,-12.5],[41.3,-12.5]],"c":true},"ix":2},"nm":"1","mn":"ADBE Vector Shape - Group","hd":false}],"nm":"1","np":3,"cix":2,"bm":0,"ix":1,"mn":"ADBE Vector Group","hd":false}]},"fFamily":"Nunito Sans"},{"ch":"8","size":56,"style":"ExtraBold","w":60,"data":{"shapes":[{"ty":"gr","it":[{"ind":0,"ty":"sh","ix":1,"ks":{"a":0,"k":{"i":[[4.066,1.2],[-1.934,2.867],[0,3.8],[4.5,3.4],[7.866,0],[4.533,-3.433],[0,-5.866],[-1.934,-2.8],[-3.467,-1.333],[2.2,-2.933],[0,-4.4],[-4.8,-3.533],[-8.467,0],[-4.8,3.534],[0,6.267],[2.2,2.967]],"o":[[3.4,-1.133],[1.933,-2.866],[0,-5.933],[-4.5,-3.4],[-7.8,0],[-4.534,3.434],[0,3.734],[1.933,2.8],[-4.134,1.134],[-2.2,2.934],[0,6.267],[4.8,3.534],[8.466,0],[4.8,-3.533],[0,-4.266],[-2.2,-2.966]],"v":[[44.4,-36.3],[52.4,-42.3],[55.3,-52.3],[48.55,-66.3],[30,-71.4],[11.5,-66.25],[4.7,-52.3],[7.6,-42.5],[15.7,-36.3],[6.2,-30.2],[2.9,-19.2],[10.1,-4.5],[30,0.8],[49.9,-4.5],[57.1,-19.2],[53.8,-30.05]],"c":true},"ix":2},"nm":"8","mn":"ADBE Vector Shape - Group","hd":false},{"ind":1,"ty":"sh","ix":2,"ks":{"a":0,"k":{"i":[[-7.134,0],[0,-5.933],[7.133,0],[0,6]],"o":[[7.133,0],[0,6],[-7.134,0],[0,-5.933]],"v":[[30,-59.5],[40.7,-50.6],[30,-41.6],[19.3,-50.6]],"c":true},"ix":2},"nm":"8","mn":"ADBE Vector Shape - Group","hd":false},{"ind":2,"ty":"sh","ix":3,"ks":{"a":0,"k":{"i":[[8.4,0],[0,6.2],[-8.4,0],[0,-6.2]],"o":[[-8.4,0],[0,-6.2],[8.4,0],[0,6.2]],"v":[[30,-11.1],[17.4,-20.4],[30,-29.7],[42.6,-20.4]],"c":true},"ix":2},"nm":"8","mn":"ADBE Vector Shape - Group","hd":false}],"nm":"8","np":6,"cix":2,"bm":0,"ix":1,"mn":"ADBE Vector Group","hd":false}]},"fFamily":"Nunito Sans"},{"ch":"3","size":56,"style":"ExtraBold","w":60,"data":{"shapes":[{"ty":"gr","it":[{"ind":0,"ty":"sh","ix":1,"ks":{"a":0,"k":{"i":[[4.133,1.2],[-1.967,2.834],[0,3.8],[1.966,2.867],[3.6,1.567],[4.8,0],[4.433,-1.433],[2.8,-2.4],[0,0],[-3.2,1.167],[-2.934,0],[-1.734,-1.533],[0,-2.866],[1.966,-1.4],[4.066,0],[0,0],[0,0],[0,0],[-1.934,-1.4],[0,-3.133],[1.933,-1.5],[4.266,0],[6.4,4.534],[0,0],[-4.467,-1.4],[-4.867,0],[-4.734,3.567],[0,6.2],[2.233,2.967]],"o":[[3.466,-1.266],[1.966,-2.833],[0,-3.8],[-1.967,-2.866],[-3.6,-1.566],[-4.667,0],[-4.434,1.434],[0,0],[3,-2.2],[3.2,-1.166],[3.266,0],[1.733,1.534],[0,2.934],[-1.967,1.4],[0,0],[0,0],[0,0],[4.266,0],[1.933,1.4],[0,3.2],[-1.934,1.5],[-6.467,0],[0,0],[2.8,2.467],[4.466,1.4],[8.066,0],[4.733,-3.566],[0,-4.266],[-2.234,-2.966]],"v":[[41.7,-36.3],[49.85,-42.45],[52.8,-52.4],[49.85,-62.4],[41.5,-69.05],[28.9,-71.4],[15.25,-69.25],[4.4,-63.5],[9.3,-52.4],[18.6,-57.45],[27.8,-59.2],[35.3,-56.9],[37.9,-50.3],[34.95,-43.8],[25.9,-41.7],[17.5,-41.7],[17.5,-29.6],[27.6,-29.6],[36.9,-27.5],[39.8,-20.7],[36.9,-13.65],[27.6,-11.4],[8.3,-18.2],[3.4,-7.1],[14.3,-1.3],[28.3,0.8],[47.5,-4.55],[54.6,-19.2],[51.25,-30.05]],"c":true},"ix":2},"nm":"3","mn":"ADBE Vector Shape - Group","hd":false}],"nm":"3","np":3,"cix":2,"bm":0,"ix":1,"mn":"ADBE Vector Group","hd":false}]},"fFamily":"Nunito Sans"},{"ch":"2","size":56,"style":"ExtraBold","w":60.1,"data":{"shapes":[{"ty":"gr","it":[{"ind":0,"ty":"sh","ix":1,"ks":{"a":0,"k":{"i":[[0,0],[0,0],[-1.7,3.467],[0,4.067],[4.366,3.534],[7.333,0],[4.4,-1.433],[2.8,-2.4],[0,0],[-3.2,1.167],[-2.934,0],[0,-5.6],[4.933,-5.2],[0,0],[0,0],[0,0],[0,0]],"o":[[0,0],[4,-4.266],[1.7,-3.466],[0,-5.933],[-4.367,-3.533],[-4.6,0],[-4.4,1.434],[0,0],[3.066,-2.2],[3.2,-1.166],[6.4,0],[0,4.4],[0,0],[0,0],[0,0],[0,0],[0,0]],"v":[[26,-12.5],[41.7,-29],[50.25,-40.6],[52.8,-51.9],[46.25,-66.1],[28.7,-71.4],[15.2,-69.25],[4.4,-63.5],[9.3,-52.4],[18.7,-57.45],[27.9,-59.2],[37.5,-50.8],[30.1,-36.4],[6.6,-11.5],[6.6,0],[55.1,0],[55.1,-12.5]],"c":true},"ix":2},"nm":"2","mn":"ADBE Vector Shape - Group","hd":false}],"nm":"2","np":3,"cix":2,"bm":0,"ix":1,"mn":"ADBE Vector Group","hd":false}]},"fFamily":"Nunito Sans"},{"ch":"7","size":56,"style":"ExtraBold","w":60,"data":{"shapes":[{"ty":"gr","it":[{"ind":0,"ty":"sh","ix":1,"ks":{"a":0,"k":{"i":[[0,0],[0,0],[0,0],[0,0],[0,0],[0,0],[0,0]],"o":[[0,0],[0,0],[0,0],[0,0],[0,0],[0,0],[0,0]],"v":[[4.7,-58],[38.7,-58],[7.4,0],[24,0],[55.4,-58.9],[55.4,-70.5],[4.7,-70.5]],"c":true},"ix":2},"nm":"7","mn":"ADBE Vector Shape - Group","hd":false}],"nm":"7","np":3,"cix":2,"bm":0,"ix":1,"mn":"ADBE Vector Group","hd":false}]},"fFamily":"Nunito Sans"},{"ch":"9","size":56,"style":"ExtraBold","w":60,"data":{"shapes":[{"ty":"gr","it":[{"ind":0,"ty":"sh","ix":1,"ks":{"a":0,"k":{"i":[[9.133,0],[3.666,-2.033],[2.066,-3.633],[0,-4.6],[-1.834,-3.466],[-3.234,-1.933],[-4.134,0],[-2.8,1.5],[-1.534,2.534],[2.5,-3.666],[4.6,0],[6.133,4.534],[0,0],[-4.067,-1.366],[-4.334,0],[-4.5,2.967],[-2.367,5.567],[0,7.734],[5,6.067]],"o":[[-4.6,0],[-3.667,2.034],[-2.067,3.634],[0,4.4],[1.833,3.467],[3.233,1.934],[3.466,0],[2.8,-1.5],[-0.334,7.134],[-2.5,3.667],[-5.467,0],[0,0],[2.866,2.534],[4.066,1.366],[6.133,0],[4.5,-2.966],[2.366,-5.566],[0,-11.266],[-5,-6.066]],"v":[[27.6,-71.4],[15.2,-68.35],[6.6,-59.85],[3.5,-47.5],[6.25,-35.7],[13.85,-27.6],[24.9,-24.7],[34.3,-26.95],[40.8,-33],[36.55,-16.8],[25.9,-11.3],[8.5,-18.1],[3.5,-7],[13.9,-1.15],[26.5,0.9],[42.45,-3.55],[52.75,-16.35],[56.3,-36.3],[48.8,-62.3]],"c":true},"ix":2},"nm":"9","mn":"ADBE Vector Shape - Group","hd":false},{"ind":1,"ty":"sh","ix":2,"ks":{"a":0,"k":{"i":[[3.133,0],[1.9,2.067],[0,3.334],[-1.9,2.067],[-3.134,0],[-1.934,-2.1],[0,-3.333],[1.933,-2.066]],"o":[[-3.134,0],[-1.9,-2.066],[0,-3.4],[1.9,-2.066],[3.133,0],[1.933,2.1],[0,3.334],[-1.934,2.067]],"v":[[28.5,-36.8],[20.95,-39.9],[18.1,-48],[20.95,-56.2],[28.5,-59.3],[36.1,-56.15],[39,-48],[36.1,-39.9]],"c":true},"ix":2},"nm":"9","mn":"ADBE Vector Shape - Group","hd":false}],"nm":"9","np":5,"cix":2,"bm":0,"ix":1,"mn":"ADBE Vector Group","hd":false}]},"fFamily":"Nunito Sans"},{"ch":"5","size":56,"style":"ExtraBold","w":60,"data":{"shapes":[{"ty":"gr","it":[{"ind":0,"ty":"sh","ix":1,"ks":{"a":0,"k":{"i":[[4.333,0],[3.2,-1.8],[0,0],[0,0],[0,0],[0,0],[0,0],[0,0],[-2.3,0.867],[-2.334,0],[-2.167,-2],[0,-3.466],[2.1,-1.866],[4.066,0],[6.466,4.534],[0,0],[-4.4,-1.433],[-4.467,0],[-4.1,1.967],[-2.234,3.6],[0,4.734],[1.866,3.4],[3.4,1.9]],"o":[[-4.334,0],[0,0],[0,0],[0,0],[0,0],[0,0],[0,0],[1.866,-1.533],[2.3,-0.866],[3.733,0],[2.166,2],[0,3.667],[-2.1,1.867],[-6.4,0],[0,0],[2.733,2.4],[4.4,1.433],[5.466,0],[4.1,-1.966],[2.233,-3.6],[0,-4.466],[-1.867,-3.4],[-3.4,-1.9]],"v":[[34.3,-45.6],[23,-42.9],[23,-58.6],[53.2,-58.6],[53.2,-70.5],[7.8,-70.5],[7.8,-28.8],[16.7,-28.8],[22.95,-32.4],[29.9,-33.7],[38.75,-30.7],[42,-22.5],[38.85,-14.2],[29.6,-11.4],[10.3,-18.2],[5.4,-7.1],[16.1,-1.35],[29.4,0.8],[43.75,-2.15],[53.25,-10.5],[56.6,-23],[53.8,-34.8],[45.9,-42.75]],"c":true},"ix":2},"nm":"5","mn":"ADBE Vector Shape - Group","hd":false}],"nm":"5","np":3,"cix":2,"bm":0,"ix":1,"mn":"ADBE Vector Group","hd":false}]},"fFamily":"Nunito Sans"},{"ch":"6","size":56,"style":"ExtraBold","w":60,"data":{"shapes":[{"ty":"gr","it":[{"ind":0,"ty":"sh","ix":1,"ks":{"a":0,"k":{"i":[[4.133,0],[2.8,-1.5],[1.533,-2.533],[-2.567,3.7],[-4.534,0],[-6.134,-4.533],[0,0],[4.066,1.367],[4.333,0],[4.466,-2.966],[2.4,-5.566],[0,-7.733],[-5,-6.066],[-9.134,0],[-3.667,2.034],[-2.067,3.634],[0,4.6],[1.833,3.467],[3.233,1.934]],"o":[[-3.467,0],[-2.8,1.5],[0.266,-7.066],[2.566,-3.7],[5.466,0],[0,0],[-2.867,-2.533],[-4.067,-1.366],[-6.134,0],[-4.467,2.967],[-2.4,5.567],[0,11.267],[5,6.067],[4.6,0],[3.666,-2.033],[2.066,-3.633],[0,-4.4],[-1.834,-3.466],[-3.234,-1.933]],"v":[[35.1,-45.8],[25.7,-43.55],[19.2,-37.5],[23.45,-53.65],[34.1,-59.2],[51.5,-52.4],[56.5,-63.5],[46.1,-69.35],[33.5,-71.4],[17.6,-66.95],[7.3,-54.15],[3.7,-34.2],[11.2,-8.2],[32.4,0.9],[44.8,-2.15],[53.4,-10.65],[56.5,-23],[53.75,-34.8],[46.15,-42.9]],"c":true},"ix":2},"nm":"6","mn":"ADBE Vector Shape - Group","hd":false},{"ind":1,"ty":"sh","ix":2,"ks":{"a":0,"k":{"i":[[3.133,0],[1.933,2.1],[0,3.334],[-1.934,2.067],[-3.134,0],[-1.9,-2.066],[0,-3.333],[1.9,-2.066]],"o":[[-3.134,0],[-1.934,-2.1],[0,-3.333],[1.933,-2.066],[3.133,0],[1.9,2.067],[0,3.4],[-1.9,2.067]],"v":[[31.5,-11.2],[23.9,-14.35],[21,-22.5],[23.9,-30.6],[31.5,-33.7],[39.05,-30.6],[41.9,-22.5],[39.05,-14.3]],"c":true},"ix":2},"nm":"6","mn":"ADBE Vector Shape - Group","hd":false}],"nm":"6","np":5,"cix":2,"bm":0,"ix":1,"mn":"ADBE Vector Group","hd":false}]},"fFamily":"Nunito Sans"},{"ch":".","size":56,"style":"ExtraBold","w":26,"data":{"shapes":[{"ty":"gr","it":[{"ind":0,"ty":"sh","ix":1,"ks":{"a":0,"k":{"i":[[0,0],[0,0],[0,0],[0,0]],"o":[[0,0],[0,0],[0,0],[0,0]],"v":[[4.9,0],[21.1,0],[21.1,-16],[4.9,-16]],"c":true},"ix":2},"nm":".","mn":"ADBE Vector Shape - Group","hd":false}],"nm":".","np":3,"cix":2,"bm":0,"ix":1,"mn":"ADBE Vector Group","hd":false}]},"fFamily":"Nunito Sans"},{"ch":"I","size":16,"style":"Regular","w":33,"data":{"shapes":[{"ty":"gr","it":[{"ind":0,"ty":"sh","ix":1,"ks":{"a":0,"k":{"i":[[0,0],[0,0],[0,0],[0,0]],"o":[[0,0],[0,0],[0,0],[0,0]],"v":[[9.164,0],[24.069,0],[24.069,-74.524],[9.164,-74.524]],"c":true},"ix":2},"nm":"I","mn":"ADBE Vector Shape - Group","hd":false}],"nm":"I","np":3,"cix":2,"bm":0,"ix":1,"mn":"ADBE Vector Group","hd":false}]},"fFamily":"Noto Sans TC Bold"},{"ch":"N","size":16,"style":"Regular","w":74.9,"data":{"shapes":[{"ty":"gr","it":[{"ind":0,"ty":"sh","ix":1,"ks":{"a":0,"k":{"i":[[0,0],[0,0],[0,0],[0.705,8.057],[0,0],[0,0],[0,0],[0,0],[0,0],[0,0],[0,0],[-0.806,-7.755],[0,0],[0,0],[0,0],[0,0]],"o":[[0,0],[0,0],[0,-8.56],[0,0],[0,0],[0,0],[0,0],[0,0],[0,0],[0,0],[0,8.459],[0,0],[0,0],[0,0],[0,0],[0,0]],"v":[[9.164,0],[23.264,0],[23.264,-29.91],[21.451,-55.893],[21.954,-55.893],[29.507,-39.88],[51.059,0],[66.165,0],[66.165,-74.524],[52.066,-74.524],[52.066,-44.815],[53.979,-18.732],[53.476,-18.732],[46.024,-34.845],[24.371,-74.524],[9.164,-74.524]],"c":true},"ix":2},"nm":"N","mn":"ADBE Vector Shape - Group","hd":false}],"nm":"N","np":3,"cix":2,"bm":0,"ix":1,"mn":"ADBE Vector Group","hd":false}]},"fFamily":"Noto Sans TC Bold"},{"ch":"C","size":16,"style":"Regular","w":61.8,"data":{"shapes":[{"ty":"gr","it":[{"ind":0,"ty":"sh","ix":1,"ks":{"a":0,"k":{"i":[[-18.832,0],[-6.143,7.15],[0,0],[6.345,0],[0,16.214],[-11.279,0],[-3.726,-3.625],[0,0],[9.467,0],[0,-24.573]],"o":[[9.668,0],[0,0],[-4.028,4.33],[-11.783,0],[0,-16.013],[5.64,0],[0,0],[-4.834,-5.035],[-18.832,0],[0,24.875]],"v":[[39.578,1.41],[63.345,-9.567],[55.49,-18.832],[40.082,-11.481],[20.645,-37.463],[40.384,-63.144],[54.08,-56.9],[61.935,-66.367],[40.082,-75.934],[5.438,-36.96]],"c":true},"ix":2},"nm":"C","mn":"ADBE Vector Shape - Group","hd":false}],"nm":"C","np":3,"cix":2,"bm":0,"ix":1,"mn":"ADBE Vector Group","hd":false}]},"fFamily":"Noto Sans TC Bold"},{"ch":"R","size":16,"style":"Regular","w":68.2,"data":{"shapes":[{"ty":"gr","it":[{"ind":0,"ty":"sh","ix":1,"ks":{"a":0,"k":{"i":[[0,0],[0,0],[0,-8.057],[9.567,0],[0,0]],"o":[[0,0],[9.567,0],[0,7.956],[0,0],[0,0]],"v":[[24.069,-62.741],[33.737,-62.741],[48.541,-51.965],[33.737,-39.981],[24.069,-39.981]],"c":true},"ix":2},"nm":"R","mn":"ADBE Vector Shape - Group","hd":false},{"ind":1,"ty":"sh","ix":2,"ks":{"a":0,"k":{"i":[[0,0],[0,0],[0,11.179],[15.61,0],[0,0],[0,0],[0,0],[0,0],[0,0],[0,0]],"o":[[0,0],[8.56,-3.323],[0,-17.12],[0,0],[0,0],[0,0],[0,0],[0,0],[0,0],[0,0]],"v":[[66.367,0],[48.944,-30.515],[63.144,-51.965],[35.147,-74.524],[9.164,-74.524],[9.164,0],[24.069,0],[24.069,-28.198],[34.442,-28.198],[49.75,0]],"c":true},"ix":2},"nm":"R","mn":"ADBE Vector Shape - Group","hd":false}],"nm":"R","np":5,"cix":2,"bm":0,"ix":1,"mn":"ADBE Vector Group","hd":false}]},"fFamily":"Noto Sans TC Bold"},{"ch":"E","size":16,"style":"Regular","w":61.5,"data":{"shapes":[{"ty":"gr","it":[{"ind":0,"ty":"sh","ix":1,"ks":{"a":0,"k":{"i":[[0,0],[0,0],[0,0],[0,0],[0,0],[0,0],[0,0],[0,0],[0,0],[0,0],[0,0],[0,0]],"o":[[0,0],[0,0],[0,0],[0,0],[0,0],[0,0],[0,0],[0,0],[0,0],[0,0],[0,0],[0,0]],"v":[[9.164,0],[55.994,0],[55.994,-12.488],[24.069,-12.488],[24.069,-32.428],[50.253,-32.428],[50.253,-44.916],[24.069,-44.916],[24.069,-62.137],[54.886,-62.137],[54.886,-74.524],[9.164,-74.524]],"c":true},"ix":2},"nm":"E","mn":"ADBE Vector Shape - Group","hd":false}],"nm":"E","np":3,"cix":2,"bm":0,"ix":1,"mn":"ADBE Vector Group","hd":false}]},"fFamily":"Noto Sans TC Bold"},{"ch":"A","size":16,"style":"Regular","w":63.8,"data":{"shapes":[{"ty":"gr","it":[{"ind":0,"ty":"sh","ix":1,"ks":{"a":0,"k":{"i":[[0,0],[0,0],[-1.913,8.157],[0,0],[-2.316,-7.755],[0,0]],"o":[[0,0],[2.216,-7.755],[0,0],[2.216,8.057],[0,0],[0,0]],"v":[[23.163,-30.716],[25.378,-38.873],[31.723,-63.245],[32.126,-63.245],[38.672,-38.873],[40.887,-30.716]],"c":true},"ix":2},"nm":"A","mn":"ADBE Vector Shape - Group","hd":false},{"ind":1,"ty":"sh","ix":2,"ks":{"a":0,"k":{"i":[[0,0],[0,0],[0,0],[0,0],[0,0],[0,0],[0,0],[0,0]],"o":[[0,0],[0,0],[0,0],[0,0],[0,0],[0,0],[0,0],[0,0]],"v":[[49.347,0],[64.957,0],[40.988,-74.524],[23.465,-74.524],[-0.403,0],[14.703,0],[19.94,-19.135],[44.11,-19.135]],"c":true},"ix":2},"nm":"A","mn":"ADBE Vector Shape - Group","hd":false}],"nm":"A","np":5,"cix":2,"bm":0,"ix":1,"mn":"ADBE Vector Group","hd":false}]},"fFamily":"Noto Sans TC Bold"},{"ch":"S","size":16,"style":"Regular","w":60.5,"data":{"shapes":[{"ty":"gr","it":[{"ind":0,"ty":"sh","ix":1,"ks":{"a":0,"k":{"i":[[-9.97,0],[0,12.186],[9.064,3.726],[0,0],[0,5.338],[-6.546,0],[-4.733,-3.928],[0,0],[8.661,0],[0,-12.186],[-7.553,-3.122],[0,0],[0,-5.539],[7.755,0],[5.338,4.935],[0,0]],"o":[[17.221,0],[0,-10.776],[0,0],[-6.345,-2.518],[0,-4.935],[6.143,0],[0,0],[-6.042,-6.143],[-15.106,0],[0,10.876],[0,0],[6.647,2.82],[0,5.237],[-6.546,0],[0,0],[7.251,6.949]],"v":[[31.421,1.41],[58.813,-21.149],[43.808,-41.391],[34.039,-45.52],[22.357,-55.289],[33.133,-63.144],[48.944,-57.001],[56.497,-66.367],[33.133,-75.934],[7.352,-54.382],[22.458,-34.341],[32.428,-30.112],[43.607,-20.041],[31.723,-11.481],[12.79,-19.739],[4.23,-9.467]],"c":true},"ix":2},"nm":"S","mn":"ADBE Vector Shape - Group","hd":false}],"nm":"S","np":3,"cix":2,"bm":0,"ix":1,"mn":"ADBE Vector Group","hd":false}]},"fFamily":"Noto Sans TC Bold"},{"ch":" ","size":16,"style":"Regular","w":22.7,"data":{},"fFamily":"Noto Sans TC Bold"},{"ch":"\r","size":16,"style":"Regular","w":0,"fFamily":"Noto Sans TC Bold"},{"ch":"P","size":16,"style":"Regular","w":66.7,"data":{"shapes":[{"ty":"gr","it":[{"ind":0,"ty":"sh","ix":1,"ks":{"a":0,"k":{"i":[[0,0],[0,0],[0,0],[0,0],[0,17.02],[16.516,0],[0,0]],"o":[[0,0],[0,0],[0,0],[16.013,0],[0,-17.624],[0,0],[0,0]],"v":[[9.164,0],[24.069,0],[24.069,-26.486],[34.039,-26.486],[62.842,-51.16],[33.636,-74.524],[9.164,-74.524]],"c":true},"ix":2},"nm":"P","mn":"ADBE Vector Shape - Group","hd":false},{"ind":1,"ty":"sh","ix":2,"ks":{"a":0,"k":{"i":[[0,0],[0,0],[0,0],[0,-8.661],[10.272,0]],"o":[[0,0],[0,0],[10.272,0],[0,8.56],[0,0]],"v":[[24.069,-38.269],[24.069,-62.741],[32.529,-62.741],[48.239,-51.16],[33.032,-38.269]],"c":true},"ix":2},"nm":"P","mn":"ADBE Vector Shape - Group","hd":false}],"nm":"P","np":5,"cix":2,"bm":0,"ix":1,"mn":"ADBE Vector Group","hd":false}]},"fFamily":"Noto Sans TC Bold"},{"ch":"O","size":16,"style":"Regular","w":77,"data":{"shapes":[{"ty":"gr","it":[{"ind":0,"ty":"sh","ix":1,"ks":{"a":0,"k":{"i":[[-19.739,0],[0,24.17],[19.739,0],[0,-24.271]],"o":[[19.739,0],[0,-24.17],[-19.739,0],[0,24.17]],"v":[[38.773,1.41],[72.107,-37.564],[38.773,-75.934],[5.438,-37.564]],"c":true},"ix":2},"nm":"O","mn":"ADBE Vector Shape - Group","hd":false},{"ind":1,"ty":"sh","ix":2,"ks":{"a":0,"k":{"i":[[11.078,0],[0,15.912],[-11.078,0],[0,-16.013]],"o":[[-11.078,0],[0,-16.013],[11.078,0],[0,15.912]],"v":[[38.773,-11.481],[20.645,-37.564],[38.773,-63.144],[56.9,-37.564]],"c":true},"ix":2},"nm":"O","mn":"ADBE Vector Shape - Group","hd":false}],"nm":"O","np":5,"cix":2,"bm":0,"ix":1,"mn":"ADBE Vector Group","hd":false}]},"fFamily":"Noto Sans TC Bold"},{"ch":"D","size":16,"style":"Regular","w":71.4,"data":{"shapes":[{"ty":"gr","it":[{"ind":0,"ty":"sh","ix":1,"ks":{"a":0,"k":{"i":[[0,0],[0,0],[0,25.076],[22.76,0],[0,0]],"o":[[0,0],[21.954,0],[0,-25.177],[0,0],[0,0]],"v":[[9.164,0],[30.414,0],[66.467,-37.564],[29.608,-74.524],[9.164,-74.524]],"c":true},"ix":2},"nm":"D","mn":"ADBE Vector Shape - Group","hd":false},{"ind":1,"ty":"sh","ix":2,"ks":{"a":0,"k":{"i":[[0,0],[0,0],[0,0],[0,-18.228],[13.898,0]],"o":[[0,0],[0,0],[13.898,0],[0,18.127],[0,0]],"v":[[24.069,-11.984],[24.069,-62.64],[28.702,-62.64],[51.26,-37.564],[28.702,-11.984]],"c":true},"ix":2},"nm":"D","mn":"ADBE Vector Shape - Group","hd":false}],"nm":"D","np":5,"cix":2,"bm":0,"ix":1,"mn":"ADBE Vector Group","hd":false}]},"fFamily":"Noto Sans TC Bold"},{"ch":"U","size":16,"style":"Regular","w":74.8,"data":{"shapes":[{"ty":"gr","it":[{"ind":0,"ty":"sh","ix":1,"ks":{"a":0,"k":{"i":[[-18.127,0],[0,24.774],[0,0],[0,0],[0,0],[8.862,0],[0,15.509],[0,0],[0,0],[0,0]],"o":[[18.228,0],[0,0],[0,0],[0,0],[0,15.509],[-8.762,0],[0,0],[0,0],[0,0],[0,24.774]],"v":[[37.766,1.41],[66.568,-33.536],[66.568,-74.524],[52.267,-74.524],[52.267,-32.227],[37.766,-11.481],[23.666,-32.227],[23.666,-74.524],[8.762,-74.524],[8.762,-33.536]],"c":true},"ix":2},"nm":"U","mn":"ADBE Vector Shape - Group","hd":false}],"nm":"U","np":3,"cix":2,"bm":0,"ix":1,"mn":"ADBE Vector Group","hd":false}]},"fFamily":"Noto Sans TC Bold"},{"ch":"T","size":16,"style":"Regular","w":62.5,"data":{"shapes":[{"ty":"gr","it":[{"ind":0,"ty":"sh","ix":1,"ks":{"a":0,"k":{"i":[[0,0],[0,0],[0,0],[0,0],[0,0],[0,0],[0,0],[0,0]],"o":[[0,0],[0,0],[0,0],[0,0],[0,0],[0,0],[0,0],[0,0]],"v":[[23.969,0],[38.873,0],[38.873,-62.137],[60.022,-62.137],[60.022,-74.524],[3.021,-74.524],[3.021,-62.137],[23.969,-62.137]],"c":true},"ix":2},"nm":"T","mn":"ADBE Vector Shape - Group","hd":false}],"nm":"T","np":3,"cix":2,"bm":0,"ix":1,"mn":"ADBE Vector Group","hd":false}]},"fFamily":"Noto Sans TC Bold"},{"ch":"V","size":16,"style":"Regular","w":63,"data":{"shapes":[{"ty":"gr","it":[{"ind":0,"ty":"sh","ix":1,"ks":{"a":0,"k":{"i":[[0,0],[0,0],[0,0],[0,0],[0,0],[2.316,-8.359],[0,0],[2.316,8.258],[0,0],[0,0]],"o":[[0,0],[0,0],[0,0],[0,0],[-2.316,8.258],[0,0],[-2.417,-8.359],[0,0],[0,0],[0,0]],"v":[[22.256,0],[39.981,0],[62.842,-74.524],[47.736,-74.524],[38.068,-38.269],[31.723,-14.2],[31.219,-14.2],[24.976,-38.269],[15.106,-74.524],[-0.504,-74.524]],"c":true},"ix":2},"nm":"V","mn":"ADBE Vector Shape - Group","hd":false}],"nm":"V","np":3,"cix":2,"bm":0,"ix":1,"mn":"ADBE Vector Group","hd":false}]},"fFamily":"Noto Sans TC Bold"},{"ch":"Y","size":16,"style":"Regular","w":58.1,"data":{"shapes":[{"ty":"gr","it":[{"ind":0,"ty":"sh","ix":1,"ks":{"a":0,"k":{"i":[[0,0],[0,0],[0,0],[0,0],[0,0],[0,0],[2.316,-5.74],[0,0],[2.115,5.539],[0,0],[0,0],[0,0]],"o":[[0,0],[0,0],[0,0],[0,0],[0,0],[-2.115,5.539],[0,0],[-2.316,-5.74],[0,0],[0,0],[0,0],[0,0]],"v":[[21.753,0],[36.658,0],[36.658,-27.292],[59.116,-74.524],[43.607,-74.524],[36.154,-56.396],[29.507,-39.88],[29.105,-39.88],[22.659,-56.396],[15.207,-74.524],[-0.604,-74.524],[21.753,-27.292]],"c":true},"ix":2},"nm":"Y","mn":"ADBE Vector Shape - Group","hd":false}],"nm":"Y","np":3,"cix":2,"bm":0,"ix":1,"mn":"ADBE Vector Group","hd":false}]},"fFamily":"Noto Sans TC Bold"},{"ch":"&","size":16,"style":"Regular","w":73.9,"data":{"shapes":[{"ty":"gr","it":[{"ind":0,"ty":"sh","ix":1,"ks":{"a":0,"k":{"i":[[0,6.345],[-3.625,3.122],[-6.345,-5.237],[3.625,0]],"o":[[0,-4.028],[4.733,6.244],[-3.525,2.316],[-7.15,0]],"v":[[17.12,-20.645],[23.264,-31.119],[40.082,-13.696],[29.205,-9.97]],"c":true},"ix":2},"nm":"&","mn":"ADBE Vector Shape - Group","hd":false},{"ind":1,"ty":"sh","ix":2,"ks":{"a":0,"k":{"i":[[0,3.122],[-4.33,0],[0,-3.726],[5.841,-3.525]],"o":[[0,-5.539],[3.928,0],[0,5.438],[-1.712,-3.525]],"v":[[24.573,-57.001],[32.025,-66.064],[37.665,-59.619],[27.292,-47.031]],"c":true},"ix":2},"nm":"&","mn":"ADBE Vector Shape - Group","hd":false},{"ind":2,"ty":"sh","ix":3,"ks":{"a":0,"k":{"i":[[0,0],[4.834,2.719],[-2.719,9.164],[0,0],[3.928,-5.237],[4.431,5.539],[0,9.869],[10.574,0],[0,-10.373],[-3.021,-5.64],[0,-10.373],[-15.61,0],[-6.143,4.834],[-5.841,-1.309]],"o":[[-3.827,-0.705],[5.74,-7.755],[0,0],[-2.014,7.352],[-5.942,-4.532],[7.956,-5.539],[0,-9.769],[-11.984,0],[0,4.935],[-7.452,4.733],[0,11.581],[9.164,0],[6.244,3.928],[0,0]],"v":[[72.409,-10.675],[59.216,-16.013],[71.805,-41.592],[58.411,-41.592],[49.246,-22.659],[33.133,-38.168],[49.146,-59.72],[31.824,-75.934],[12.286,-57.001],[17.02,-40.887],[3.021,-19.739],[27.393,1.41],[50.253,-6.445],[68.784,1.41]],"c":true},"ix":2},"nm":"&","mn":"ADBE Vector Shape - Group","hd":false}],"nm":"&","np":6,"cix":2,"bm":0,"ix":1,"mn":"ADBE Vector Group","hd":false}]},"fFamily":"Noto Sans TC Bold"},{"ch":"G","size":16,"style":"Regular","w":71.7,"data":{"shapes":[{"ty":"gr","it":[{"ind":0,"ty":"sh","ix":1,"ks":{"a":0,"k":{"i":[[-20.343,0],[-5.035,4.935],[0,0],[0,0],[0,0],[0,0],[0,0],[3.625,0],[0,16.214],[-12.387,0],[-3.625,-3.525],[0,0],[10.776,0],[0,-24.573]],"o":[[10.373,0],[0,0],[0,0],[0,0],[0,0],[0,0],[-2.115,1.813],[-14.603,0],[0,-16.013],[6.747,0],[0,0],[-4.834,-4.935],[-19.839,0],[0,24.875]],"v":[[41.19,1.41],[65.359,-7.553],[65.359,-41.19],[38.873,-41.19],[38.873,-29.004],[52.066,-29.004],[52.066,-14.301],[42.7,-11.481],[20.645,-37.463],[41.693,-63.144],[56.296,-56.9],[64.252,-66.367],[41.19,-75.934],[5.438,-36.96]],"c":true},"ix":2},"nm":"G","mn":"ADBE Vector Shape - Group","hd":false}],"nm":"G","np":3,"cix":2,"bm":0,"ix":1,"mn":"ADBE Vector Group","hd":false}]},"fFamily":"Noto Sans TC Bold"},{"ch":"H","size":16,"style":"Regular","w":75.7,"data":{"shapes":[{"ty":"gr","it":[{"ind":0,"ty":"sh","ix":1,"ks":{"a":0,"k":{"i":[[0,0],[0,0],[0,0],[0,0],[0,0],[0,0],[0,0],[0,0],[0,0],[0,0],[0,0],[0,0]],"o":[[0,0],[0,0],[0,0],[0,0],[0,0],[0,0],[0,0],[0,0],[0,0],[0,0],[0,0],[0,0]],"v":[[9.164,0],[24.069,0],[24.069,-32.227],[52.267,-32.227],[52.267,0],[67.072,0],[67.072,-74.524],[52.267,-74.524],[52.267,-45.218],[24.069,-45.218],[24.069,-74.524],[9.164,-74.524]],"c":true},"ix":2},"nm":"H","mn":"ADBE Vector Shape - Group","hd":false}],"nm":"H","np":3,"cix":2,"bm":0,"ix":1,"mn":"ADBE Vector Group","hd":false}]},"fFamily":"Noto Sans TC Bold"}]}